{"active_chip": "bboost", "automatic_subs": [{"entry": 1282663, "element_in": 237, "element_out": 262, "event": 28}], "entry_history": {"event": 28, "points": 100, "total_points": 1691, "rank": 1009201, "rank_sort": 1010938, "overall_rank": 529408, "bank": 2, "value": 1034, "event_transfers": 3, "event_transfers_cost": 8, "points_on_bench": 0}, "picks": [{"element": 376, "position": 1, "multiplier": 1, "is_captain": false, "is_vice_captain": false}, {"element": 121, "position": 2, "multiplier": 1, "is_captain": false, "is_vice_captain": true}, {"element": 16, "position": 3, "multiplier": 1, "is_captain": false, "is_vice_captain": false}, {"element": 237, "position": 4, "multiplier": 1, "is_captain": false, "is_vice_captain": false}, {"element": 138, "position": 5, "multiplier": 2, "is_captain": true, "is_vice_captain": false}, {"element": 22, "position": 6, "multiplier": 1, "is_captain": false, "is_vice_captain": false}, {"element": 233, "position": 7, "multiplier": 1, "is_captain": false, "is_vice_captain": false}, {"element": 51, "position": 8, "multiplier": 1, "is_captain": false, "is_vice_captain": false}, {"element": 450, "position": 9, "multiplier": 1, "is_captain": false, "is_vice_captain": false}, {"element": 518, "position": 10, "multiplier": 1, "is_captain": false, "is_vice_captain": false}, {"element": 357, "position": 11, "multiplier": 1, "is_captain": false, "is_vice_captain": false}, {"element": 170, "position": 12, "multiplier": 1, "is_captain": false, "is_vice_captain": false}, {"element": 262, "position": 13, "multiplier": 1, "is_captain": false, "is_vice_captain": false}, {"element": 420, "position": 14, "multiplier": 1, "is_captain": false, "is_vice_captain": false}, {"element": 259, "position": 15, "multiplier": 1, "is_captain": false, "is_vice_captain": false}]}