{"fixtures": [], "history": [{"element": 101, "fixture": 8, "opponent_team": 18, "total_points": 2, "was_home": true, "kickoff_time": "2023-08-13T13:00:00Z", "team_h_score": 2, "team_a_score": 2, "round": 1, "minutes": 90, "goals_scored": 0, "assists": 0, "clean_sheets": 0, "goals_conceded": 2, "own_goals": 0, "penalties_saved": 0, "penalties_missed": 0, "yellow_cards": 0, "red_cards": 0, "saves": 4, "bonus": 0, "bps": 17, "influence": "34.8", "creativity": "0.0", "threat": "0.0", "ict_index": "3.5", "starts": 1, "expected_goals": "0.00", "expected_assists": "0.00", "expected_goal_involvements": "0.00", "expected_goals_conceded": "1.26", "value": 45, "transfers_balance": 0, "selected": 159379, "transfers_in": 0, "transfers_out": 0}, {"element": 101, "fixture": 13, "opponent_team": 10, "total_points": 6, "was_home": false, "kickoff_time": "2023-08-19T14:00:00Z", "team_h_score": 0, "team_a_score": 3, "round": 2, "minutes": 90, "goals_scored": 0, "assists": 0, "clean_sheets": 1, "goals_conceded": 0, "own_goals": 0, "penalties_saved": 0, "penalties_missed": 0, "yellow_cards": 0, "red_cards": 0, "saves": 2, "bonus": 0, "bps": 28, "influence": "19.2", "creativity": "0.0", "threat": "0.0", "ict_index": "1.9", "starts": 1, "expected_goals": "0.00", "expected_assists": "0.00", "expected_goal_involvements": "0.00", "expected_goals_conceded": "0.46", "value": 45, "transfers_balance": 7871, "selected": 181430, "transfers_in": 16379, "transfers_out": 8508}, {"element": 101, "fixture": 23, "opponent_team": 8, "total_points": 4, "was_home": true, "kickoff_time": "2023-08-26T14:00:00Z", "team_h_score": 1, "team_a_score": 1, "round": 3, "minutes": 90, "goals_scored": 0, "assists": 0, "clean_sheets": 0, "goals_conceded": 1, "own_goals": 0, "penalties_saved": 0, "penalties_missed": 0, "yellow_cards": 0, "red_cards": 0, "saves": 4, "bonus": 1, "bps": 22, "influence": "32.0", "creativity": "0.0", "threat": "0.0", "ict_index": "3.2", "starts": 1, "expected_goals": "0.00", "expected_assists": "0.00", "expected_goal_involvements": "0.00", "expected_goals_conceded": "0.80", "value": 45, "transfers_balance": 32134, "selected": 221996, "transfers_in": 48159, "transfers_out": 16025}, {"element": 101, "fixture": 32, "opponent_team": 3, "total_points": 2, "was_home": true, "kickoff_time": "2023-09-02T14:00:00Z", "team_h_score": 2, "team_a_score": 2, "round": 4, "minutes": 90, "goals_scored": 0, "assists": 0, "clean_sheets": 0, "goals_conceded": 2, "own_goals": 0, "penalties_saved": 0, "penalties_missed": 0, "yellow_cards": 0, "red_cards": 0, "saves": 3, "bonus": 0, "bps": 17, "influence": "31.4", "creativity": "0.0", "threat": "0.0", "ict_index": "3.1", "starts": 1, "expected_goals": "0.00", "expected_assists": "0.00", "expected_goal_involvements": "0.00", "expected_goals_conceded": "2.02", "value": 45, "transfers_balance": 46479, "selected": 278840, "transfers_in": 63775, "transfers_out": 17296}, {"element": 101, "fixture": 46, "opponent_team": 15, "total_points": 1, "was_home": false, "kickoff_time": "2023-09-16T16:30:00Z", "team_h_score": 1, "team_a_score": 0, "round": 5, "minutes": 90, "goals_scored": 0, "assists": 0, "clean_sheets": 0, "goals_conceded": 1, "own_goals": 0, "penalties_saved": 0, "penalties_missed": 0, "yellow_cards": 1, "red_cards": 0, "saves": 1, "bonus": 0, "bps": 6, "influence": "6.6", "creativity": "0.0", "threat": "0.0", "ict_index": "0.7", "starts": 1, "expected_goals": "0.00", "expected_assists": "0.00", "expected_goal_involvements": "0.00", "expected_goals_conceded": "1.43", "value": 45, "transfers_balance": 10622, "selected": 289170, "transfers_in": 39379, "transfers_out": 28757}, {"element": 101, "fixture": 52, "opponent_team": 9, "total_points": 2, "was_home": true, "kickoff_time": "2023-09-23T16:30:00Z", "team_h_score": 1, "team_a_score": 3, "round": 6, "minutes": 90, "goals_scored": 0, "assists": 0, "clean_sheets": 0, "goals_conceded": 3, "own_goals": 0, "penalties_saved": 0, "penalties_missed": 0, "yellow_cards": 0, "red_cards": 0, "saves": 3, "bonus": 0, "bps": 18, "influence": "23.2", "creativity": "0.0", "threat": "0.0", "ict_index": "2.3", "starts": 1, "expected_goals": "0.00", "expected_assists": "0.00", "expected_goal_involvements": "0.00", "expected_goals_conceded": "1.84", "value": 45, "transfers_balance": 91052, "selected": 388161, "transfers_in": 107282, "transfers_out": 16230}, {"element": 101, "fixture": 67, "opponent_team": 16, "total_points": 2, "was_home": false, "kickoff_time": "2023-10-01T13:00:00Z", "team_h_score": 1, "team_a_score": 1, "round": 7, "minutes": 90, "goals_scored": 0, "assists": 0, "clean_sheets": 0, "goals_conceded": 1, "own_goals": 0, "penalties_saved": 0, "penalties_missed": 0, "yellow_cards": 0, "red_cards": 0, "saves": 0, "bonus": 0, "bps": 13, "influence": "5.6", "creativity": "0.0", "threat": "0.0", "ict_index": "0.6", "starts": 1, "expected_goals": "0.00", "expected_assists": "0.00", "expected_goal_involvements": "0.00", "expected_goals_conceded": "0.47", "value": 45, "transfers_balance": -22952, "selected": 360006, "transfers_in": 9521, "transfers_out": 32473}, {"element": 101, "fixture": 78, "opponent_team": 14, "total_points": 0, "was_home": false, "kickoff_time": "2023-10-07T14:00:00Z", "team_h_score": 2, "team_a_score": 1, "round": 8, "minutes": 0, "goals_scored": 0, "assists": 0, "clean_sheets": 0, "goals_conceded": 0, "own_goals": 0, "penalties_saved": 0, "penalties_missed": 0, "yellow_cards": 0, "red_cards": 0, "saves": 0, "bonus": 0, "bps": 0, "influence": "0.0", "creativity": "0.0", "threat": "0.0", "ict_index": "0.0", "starts": 0, "expected_goals": "0.00", "expected_assists": "0.00", "expected_goal_involvements": "0.00", "expected_goals_conceded": "0.00", "value": 45, "transfers_balance": -39958, "selected": 319162, "transfers_in": 5610, "transfers_out": 45568}, {"element": 101, "fixture": 83, "opponent_team": 6, "total_points": 6, "was_home": true, "kickoff_time": "2023-10-21T14:00:00Z", "team_h_score": 3, "team_a_score": 0, "round": 9, "minutes": 90, "goals_scored": 0, "assists": 0, "clean_sheets": 1, "goals_conceded": 0, "own_goals": 0, "penalties_saved": 0, "penalties_missed": 0, "yellow_cards": 0, "red_cards": 0, "saves": 1, "bonus": 0, "bps": 24, "influence": "9.8", "creativity": "0.0", "threat": "0.0", "ict_index": "1.0", "starts": 1, "expected_goals": "0.00", "expected_assists": "0.00", "expected_goal_involvements": "0.00", "expected_goals_conceded": "1.14", "value": 45, "transfers_balance": -22075, "selected": 301633, "transfers_in": 9110, "transfers_out": 31185}, {"element": 101, "fixture": 95, "opponent_team": 7, "total_points": 6, "was_home": false, "kickoff_time": "2023-10-28T11:30:00Z", "team_h_score": 0, "team_a_score": 2, "round": 10, "minutes": 90, "goals_scored": 0, "assists": 0, "clean_sheets": 1, "goals_conceded": 0, "own_goals": 0, "penalties_saved": 0, "penalties_missed": 0, "yellow_cards": 0, "red_cards": 0, "saves": 2, "bonus": 0, "bps": 24, "influence": "17.0", "creativity": "0.0", "threat": "0.0", "ict_index": "1.7", "starts": 1, "expected_goals": "0.00", "expected_assists": "0.06", "expected_goal_involvements": "0.06", "expected_goals_conceded": "2.03", "value": 45, "transfers_balance": -15961, "selected": 286069, "transfers_in": 7472, "transfers_out": 23433}, {"element": 101, "fixture": 101, "opponent_team": 19, "total_points": 0, "was_home": true, "kickoff_time": "2023-11-04T15:00:00Z", "team_h_score": 3, "team_a_score": 2, "round": 11, "minutes": 45, "goals_scored": 0, "assists": 0, "clean_sheets": 0, "goals_conceded": 2, "own_goals": 0, "penalties_saved": 0, "penalties_missed": 0, "yellow_cards": 0, "red_cards": 0, "saves": 0, "bonus": 0, "bps": 3, "influence": "2.2", "creativity": "0.0", "threat": "0.0", "ict_index": "0.2", "starts": 1, "expected_goals": "0.00", "expected_assists": "0.00", "expected_goal_involvements": "0.00", "expected_goals_conceded": "1.84", "value": 45, "transfers_balance": 5247, "selected": 294000, "transfers_in": 14981, "transfers_out": 9734}, {"element": 101, "fixture": 117, "opponent_team": 11, "total_points": 3, "was_home": false, "kickoff_time": "2023-11-12T14:00:00Z", "team_h_score": 3, "team_a_score": 0, "round": 12, "minutes": 90, "goals_scored": 0, "assists": 0, "clean_sheets": 0, "goals_conceded": 3, "own_goals": 0, "penalties_saved": 0, "penalties_missed": 0, "yellow_cards": 0, "red_cards": 0, "saves": 8, "bonus": 0, "bps": 27, "influence": "44.6", "creativity": "0.0", "threat": "0.0", "ict_index": "4.5", "starts": 1, "expected_goals": "0.00", "expected_assists": "0.00", "expected_goal_involvements": "0.00", "expected_goals_conceded": "1.53", "value": 45, "transfers_balance": -24002, "selected": 267923, "transfers_in": 2879, "transfers_out": 26881}, {"element": 101, "fixture": 121, "opponent_team": 1, "total_points": 3, "was_home": true, "kickoff_time": "2023-11-25T17:30:00Z", "team_h_score": 0, "team_a_score": 1, "round": 13, "minutes": 90, "goals_scored": 0, "assists": 0, "clean_sheets": 0, "goals_conceded": 1, "own_goals": 0, "penalties_saved": 0, "penalties_missed": 0, "yellow_cards": 0, "red_cards": 0, "saves": 3, "bonus": 0, "bps": 13, "influence": "27.0", "creativity": "0.0", "threat": "0.0", "ict_index": "2.7", "starts": 1, "expected_goals": "0.00", "expected_assists": "0.00", "expected_goal_involvements": "0.00", "expected_goals_conceded": "1.52", "value": 45, "transfers_balance": 1726, "selected": 272125, "transfers_in": 10040, "transfers_out": 8314}, {"element": 101, "fixture": 133, "opponent_team": 12, "total_points": 2, "was_home": true, "kickoff_time": "2023-12-02T15:00:00Z", "team_h_score": 3, "team_a_score": 1, "round": 14, "minutes": 90, "goals_scored": 0, "assists": 0, "clean_sheets": 0, "goals_conceded": 1, "own_goals": 0, "penalties_saved": 0, "penalties_missed": 0, "yellow_cards": 0, "red_cards": 0, "saves": 0, "bonus": 0, "bps": 7, "influence": "5.0", "creativity": "0.0", "threat": "0.0", "ict_index": "0.5", "starts": 1, "expected_goals": "0.00", "expected_assists": "0.00", "expected_goal_involvements": "0.00", "expected_goals_conceded": "0.23", "value": 45, "transfers_balance": 59006, "selected": 339441, "transfers_in": 64836, "transfers_out": 5830}, {"element": 101, "fixture": 142, "opponent_team": 5, "total_points": 2, "was_home": false, "kickoff_time": "2023-12-06T19:30:00Z", "team_h_score": 2, "team_a_score": 1, "round": 15, "minutes": 90, "goals_scored": 0, "assists": 0, "clean_sheets": 0, "goals_conceded": 2, "own_goals": 0, "penalties_saved": 0, "penalties_missed": 0, "yellow_cards": 0, "red_cards": 0, "saves": 5, "bonus": 0, "bps": 18, "influence": "38.4", "creativity": "0.0", "threat": "0.0", "ict_index": "3.8", "starts": 1, "expected_goals": "0.00", "expected_assists": "0.00", "expected_goal_involvements": "0.00", "expected_goals_conceded": "1.52", "value": 45, "transfers_balance": -15961, "selected": 318393, "transfers_in": 10071, "transfers_out": 26032}, {"element": 101, "fixture": 158, "opponent_team": 17, "total_points": 3, "was_home": false, "kickoff_time": "2023-12-09T15:00:00Z", "team_h_score": 1, "team_a_score": 0, "round": 16, "minutes": 90, "goals_scored": 0, "assists": 0, "clean_sheets": 0, "goals_conceded": 1, "own_goals": 0, "penalties_saved": 0, "penalties_missed": 0, "yellow_cards": 0, "red_cards": 0, "saves": 3, "bonus": 0, "bps": 18, "influence": "22.4", "creativity": "0.0", "threat": "0.0", "ict_index": "2.2", "starts": 1, "expected_goals": "0.00", "expected_assists": "0.00", "expected_goal_involvements": "0.00", "expected_goals_conceded": "0.89", "value": 45, "transfers_balance": 17762, "selected": 339965, "transfers_in": 27870, "transfers_out": 10108}, {"element": 101, "fixture": 163, "opponent_team": 2, "total_points": 2, "was_home": true, "kickoff_time": "2023-12-17T14:00:00Z", "team_h_score": 1, "team_a_score": 2, "round": 17, "minutes": 90, "goals_scored": 0, "assists": 0, "clean_sheets": 0, "goals_conceded": 2, "own_goals": 0, "penalties_saved": 0, "penalties_missed": 0, "yellow_cards": 0, "red_cards": 0, "saves": 3, "bonus": 0, "bps": 14, "influence": "20.4", "creativity": "0.0", "threat": "0.0", "ict_index": "2.0", "starts": 1, "expected_goals": "0.00", "expected_assists": "0.00", "expected_goal_involvements": "0.00", "expected_goals_conceded": "1.42", "value": 45, "transfers_balance": -21771, "selected": 313881, "transfers_in": 4026, "transfers_out": 25797}, {"element": 101, "fixture": 183, "opponent_team": 20, "total_points": 0, "was_home": true, "kickoff_time": "2023-12-27T19:30:00Z", "team_h_score": 1, "team_a_score": 4, "round": 19, "minutes": 90, "goals_scored": 0, "assists": 0, "clean_sheets": 0, "goals_conceded": 4, "own_goals": 0, "penalties_saved": 0, "penalties_missed": 0, "yellow_cards": 0, "red_cards": 0, "saves": 1, "bonus": 0, "bps": 15, "influence": "13.6", "creativity": "0.0", "threat": "0.0", "ict_index": "1.4", "starts": 1, "expected_goals": "0.00", "expected_assists": "0.00", "expected_goal_involvements": "0.00", "expected_goals_conceded": "2.10", "value": 45, "transfers_balance": 3455, "selected": 300068, "transfers_in": 9753, "transfers_out": 6298}, {"element": 101, "fixture": 192, "opponent_team": 8, "total_points": 2, "was_home": false, "kickoff_time": "2023-12-30T15:00:00Z", "team_h_score": 3, "team_a_score": 1, "round": 20, "minutes": 90, "goals_scored": 0, "assists": 0, "clean_sheets": 0, "goals_conceded": 3, "own_goals": 0, "penalties_saved": 0, "penalties_missed": 0, "yellow_cards": 0, "red_cards": 0, "saves": 3, "bonus": 0, "bps": 19, "influence": "25.6", "creativity": "0.0", "threat": "0.0", "ict_index": "2.6", "starts": 1, "expected_goals": "0.00", "expected_assists": "0.00", "expected_goal_involvements": "0.00", "expected_goals_conceded": "1.08", "value": 45, "transfers_balance": -8171, "selected": 291915, "transfers_in": 6696, "transfers_out": 14867}, {"element": 101, "fixture": 203, "opponent_team": 16, "total_points": 1, "was_home": true, "kickoff_time": "2024-01-20T17:30:00Z", "team_h_score": 3, "team_a_score": 2, "round": 21, "minutes": 90, "goals_scored": 0, "assists": 0, "clean_sheets": 0, "goals_conceded": 2, "own_goals": 0, "penalties_saved": 0, "penalties_missed": 0, "yellow_cards": 0, "red_cards": 0, "saves": 1, "bonus": 0, "bps": 14, "influence": "10.2", "creativity": "0.0", "threat": "0.0", "ict_index": "1.0", "starts": 1, "expected_goals": "0.00", "expected_assists": "0.00", "expected_goal_involvements": "0.00", "expected_goals_conceded": "1.09", "value": 45, "transfers_balance": -29386, "selected": 263126, "transfers_in": 6123, "transfers_out": 35509}, {"element": 101, "fixture": 216, "opponent_team": 18, "total_points": 1, "was_home": false, "kickoff_time": "2024-01-31T19:30:00Z", "team_h_score": 3, "team_a_score": 2, "round": 22, "minutes": 90, "goals_scored": 0, "assists": 0, "clean_sheets": 0, "goals_conceded": 3, "own_goals": 0, "penalties_saved": 0, "penalties_missed": 0, "yellow_cards": 0, "red_cards": 0, "saves": 2, "bonus": 0, "bps": 12, "influence": "15.2", "creativity": "0.0", "threat": "0.0", "ict_index": "1.5", "starts": 1, "expected_goals": "0.00", "expected_assists": "0.00", "expected_goal_involvements": "0.00", "expected_goals_conceded": "2.86", "value": 45, "transfers_balance": -12810, "selected": 251102, "transfers_in": 1768, "transfers_out": 14578}, {"element": 101, "fixture": 223, "opponent_team": 13, "total_points": 10, "was_home": true, "kickoff_time": "2024-02-05T20:00:00Z", "team_h_score": 1, "team_a_score": 3, "round": 23, "minutes": 90, "goals_scored": 0, "assists": 1, "clean_sheets": 0, "goals_conceded": 3, "own_goals": 0, "penalties_saved": 0, "penalties_missed": 0, "yellow_cards": 0, "red_cards": 0, "saves": 12, "bonus": 2, "bps": 45, "influence": "84.0", "creativity": "10.0", "threat": "0.0", "ict_index": "9.4", "starts": 1, "expected_goals": "0.00", "expected_assists": "0.01", "expected_goal_involvements": "0.01", "expected_goals_conceded": "2.15", "value": 45, "transfers_balance": -8961, "selected": 242409, "transfers_in": 1350, "transfers_out": 10311}, {"element": 101, "fixture": 240, "opponent_team": 20, "total_points": 7, "was_home": false, "kickoff_time": "2024-02-10T15:00:00Z", "team_h_score": 0, "team_a_score": 2, "round": 24, "minutes": 90, "goals_scored": 0, "assists": 0, "clean_sheets": 1, "goals_conceded": 0, "own_goals": 0, "penalties_saved": 0, "penalties_missed": 0, "yellow_cards": 1, "red_cards": 0, "saves": 5, "bonus": 1, "bps": 29, "influence": "38.0", "creativity": "0.0", "threat": "0.0", "ict_index": "3.8", "starts": 1, "expected_goals": "0.00", "expected_assists": "0.00", "expected_goal_involvements": "0.00", "expected_goals_conceded": "1.13", "value": 45, "transfers_balance": 24118, "selected": 268310, "transfers_in": 35626, "transfers_out": 11508}, {"element": 101, "fixture": 241, "opponent_team": 11, "total_points": 1, "was_home": true, "kickoff_time": "2024-02-17T12:30:00Z", "team_h_score": 1, "team_a_score": 4, "round": 25, "minutes": 90, "goals_scored": 0, "assists": 0, "clean_sheets": 0, "goals_conceded": 4, "own_goals": 0, "penalties_saved": 0, "penalties_missed": 0, "yellow_cards": 0, "red_cards": 0, "saves": 4, "bonus": 0, "bps": 16, "influence": "32.0", "creativity": "0.0", "threat": "0.0", "ict_index": "3.2", "starts": 1, "expected_goals": "0.00", "expected_assists": "0.00", "expected_goal_involvements": "0.00", "expected_goals_conceded": "2.82", "value": 45, "transfers_balance": 76941, "selected": 407643, "transfers_in": 93931, "transfers_out": 16990}, {"element": 101, "fixture": 176, "opponent_team": 13, "total_points": 5, "was_home": false, "kickoff_time": "2024-02-20T19:30:00Z", "team_h_score": 1, "team_a_score": 0, "round": 25, "minutes": 90, "goals_scored": 0, "assists": 0, "clean_sheets": 0, "goals_conceded": 1, "own_goals": 0, "penalties_saved": 0, "penalties_missed": 0, "yellow_cards": 1, "red_cards": 0, "saves": 9, "bonus": 1, "bps": 25, "influence": "66.0", "creativity": "0.0", "threat": "0.0", "ict_index": "6.6", "starts": 1, "expected_goals": "0.00", "expected_assists": "0.01", "expected_goal_involvements": "0.01", "expected_goals_conceded": "2.46", "value": 45, "transfers_balance": 76941, "selected": 407643, "transfers_in": 93931, "transfers_out": 16990}, {"element": 101, "fixture": 259, "opponent_team": 19, "total_points": 0, "was_home": false, "kickoff_time": "2024-02-26T20:00:00Z", "team_h_score": 4, "team_a_score": 2, "round": 26, "minutes": 90, "goals_scored": 0, "assists": 0, "clean_sheets": 0, "goals_conceded": 4, "own_goals": 0, "penalties_saved": 0, "penalties_missed": 0, "yellow_cards": 0, "red_cards": 0, "saves": 2, "bonus": 0, "bps": 13, "influence": "12.6", "creativity": "0.0", "threat": "0.0", "ict_index": "1.3", "starts": 1, "expected_goals": "0.00", "expected_assists": "0.00", "expected_goal_involvements": "0.00", "expected_goals_conceded": "1.51", "value": 45, "transfers_balance": 22362, "selected": 379319, "transfers_in": 40667, "transfers_out": 18305}, {"element": 101, "fixture": 261, "opponent_team": 7, "total_points": 2, "was_home": true, "kickoff_time": "2024-03-02T15:00:00Z", "team_h_score": 2, "team_a_score": 2, "round": 27, "minutes": 90, "goals_scored": 0, "assists": 0, "clean_sheets": 0, "goals_conceded": 2, "own_goals": 0, "penalties_saved": 0, "penalties_missed": 0, "yellow_cards": 0, "red_cards": 0, "saves": 3, "bonus": 0, "bps": 16, "influence": "23.2", "creativity": "0.0", "threat": "0.0", "ict_index": "2.3", "starts": 1, "expected_goals": "0.00", "expected_assists": "0.01", "expected_goal_involvements": "0.01", "expected_goals_conceded": "1.81", "value": 45, "transfers_balance": 2643, "selected": 374454, "transfers_in": 20514, "transfers_out": 17871}, {"element": 101, "fixture": 271, "opponent_team": 1, "total_points": 2, "was_home": false, "kickoff_time": "2024-03-09T17:30:00Z", "team_h_score": 2, "team_a_score": 1, "round": 28, "minutes": 90, "goals_scored": 0, "assists": 0, "clean_sheets": 0, "goals_conceded": 2, "own_goals": 0, "penalties_saved": 0, "penalties_missed": 0, "yellow_cards": 0, "red_cards": 0, "saves": 4, "bonus": 0, "bps": 19, "influence": "30.0", "creativity": "0.0", "threat": "0.0", "ict_index": "3.0", "starts": 1, "expected_goals": "0.00", "expected_assists": "0.00", "expected_goal_involvements": "0.00", "expected_goals_conceded": "1.32", "value": 45, "transfers_balance": -13870, "selected": 360916, "transfers_in": 13074, "transfers_out": 26944}, {"element": 101, "fixture": 283, "opponent_team": 6, "total_points": 2, "was_home": false, "kickoff_time": "2024-03-16T15:00:00Z", "team_h_score": 2, "team_a_score": 1, "round": 29, "minutes": 90, "goals_scored": 0, "assists": 0, "clean_sheets": 0, "goals_conceded": 2, "own_goals": 0, "penalties_saved": 0, "penalties_missed": 0, "yellow_cards": 0, "red_cards": 0, "saves": 4, "bonus": 0, "bps": 20, "influence": "38.6", "creativity": "0.0", "threat": "0.0", "ict_index": "3.9", "starts": 1, "expected_goals": "0.00", "expected_assists": "0.01", "expected_goal_involvements": "0.01", "expected_goals_conceded": "2.66", "value": 45, "transfers_balance": 88944, "selected": 1369071, "transfers_in": 95386, "transfers_out": 6442}, {"element": 101, "fixture": 293, "opponent_team": 14, "total_points": 3, "was_home": true, "kickoff_time": "2024-03-30T20:00:00Z", "team_h_score": 1, "team_a_score": 1, "round": 30, "minutes": 90, "goals_scored": 0, "assists": 0, "clean_sheets": 0, "goals_conceded": 1, "own_goals": 0, "penalties_saved": 0, "penalties_missed": 0, "yellow_cards": 0, "red_cards": 0, "saves": 4, "bonus": 0, "bps": 18, "influence": "26.2", "creativity": "10.2", "threat": "0.0", "ict_index": "3.6", "starts": 1, "expected_goals": "0.00", "expected_assists": "0.03", "expected_goal_involvements": "0.03", "expected_goals_conceded": "0.50", "value": 46, "transfers_balance": -37946, "selected": 407962, "transfers_in": 3641, "transfers_out": 41587}, {"element": 101, "fixture": 303, "opponent_team": 5, "total_points": 11, "was_home": true, "kickoff_time": "2024-04-03T18:30:00Z", "team_h_score": 0, "team_a_score": 0, "round": 31, "minutes": 90, "goals_scored": 0, "assists": 0, "clean_sheets": 1, "goals_conceded": 0, "own_goals": 0, "penalties_saved": 0, "penalties_missed": 0, "yellow_cards": 0, "red_cards": 0, "saves": 6, "bonus": 3, "bps": 34, "influence": "42.4", "creativity": "10.1", "threat": "0.0", "ict_index": "5.3", "starts": 1, "expected_goals": "0.00", "expected_assists": "0.01", "expected_goal_involvements": "0.01", "expected_goals_conceded": "1.11", "value": 46, "transfers_balance": 687, "selected": 409756, "transfers_in": 12565, "transfers_out": 11878}, {"element": 101, "fixture": 311, "opponent_team": 2, "total_points": 1, "was_home": false, "kickoff_time": "2024-04-06T14:00:00Z", "team_h_score": 3, "team_a_score": 3, "round": 32, "minutes": 90, "goals_scored": 0, "assists": 0, "clean_sheets": 0, "goals_conceded": 3, "own_goals": 0, "penalties_saved": 0, "penalties_missed": 0, "yellow_cards": 0, "red_cards": 0, "saves": 0, "bonus": 0, "bps": 8, "influence": "0.0", "creativity": "0.0", "threat": "0.0", "ict_index": "0.0", "starts": 1, "expected_goals": "0.00", "expected_assists": "0.00", "expected_goal_involvements": "0.00", "expected_goals_conceded": "1.52", "value": 46, "transfers_balance": 31246, "selected": 442237, "transfers_in": 38123, "transfers_out": 6877}, {"element": 101, "fixture": 323, "opponent_team": 17, "total_points": 7, "was_home": true, "kickoff_time": "2024-04-13T14:00:00Z", "team_h_score": 2, "team_a_score": 0, "round": 33, "minutes": 90, "goals_scored": 0, "assists": 0, "clean_sheets": 1, "goals_conceded": 0, "own_goals": 0, "penalties_saved": 0, "penalties_missed": 0, "yellow_cards": 0, "red_cards": 0, "saves": 2, "bonus": 1, "bps": 25, "influence": "21.2", "creativity": "0.0", "threat": "0.0", "ict_index": "2.1", "starts": 1, "expected_goals": "0.00", "expected_assists": "0.00", "expected_goal_involvements": "0.00", "expected_goals_conceded": "0.84", "value": 46, "transfers_balance": 71373, "selected": 515244, "transfers_in": 80376, "transfers_out": 9003}, {"element": 101, "fixture": 336, "opponent_team": 12, "total_points": 2, "was_home": false, "kickoff_time": "2024-04-20T14:00:00Z", "team_h_score": 1, "team_a_score": 5, "round": 34, "minutes": 90, "goals_scored": 0, "assists": 0, "clean_sheets": 0, "goals_conceded": 1, "own_goals": 0, "penalties_saved": 0, "penalties_missed": 0, "yellow_cards": 0, "red_cards": 0, "saves": 2, "bonus": 0, "bps": 12, "influence": "19.8", "creativity": "0.0", "threat": "0.0", "ict_index": "2.0", "starts": 1, "expected_goals": "0.00", "expected_assists": "0.00", "expected_goal_involvements": "0.00", "expected_goals_conceded": "0.59", "value": 47, "transfers_balance": 17507, "selected": 517243, "transfers_in": 41734, "transfers_out": 24227}, {"element": 101, "fixture": 343, "opponent_team": 9, "total_points": 2, "was_home": false, "kickoff_time": "2024-04-27T16:30:00Z", "team_h_score": 1, "team_a_score": 0, "round": 35, "minutes": 90, "goals_scored": 0, "assists": 0, "clean_sheets": 0, "goals_conceded": 1, "own_goals": 0, "penalties_saved": 0, "penalties_missed": 0, "yellow_cards": 0, "red_cards": 0, "saves": 0, "bonus": 0, "bps": 13, "influence": "8.0", "creativity": "0.0", "threat": "0.0", "ict_index": "0.8", "starts": 1, "expected_goals": "0.00", "expected_assists": "0.00", "expected_goal_involvements": "0.00", "expected_goals_conceded": "0.77", "value": 47, "transfers_balance": -20626, "selected": 512918, "transfers_in": 12669, "transfers_out": 33295}, {"element": 101, "fixture": 352, "opponent_team": 10, "total_points": 10, "was_home": true, "kickoff_time": "2024-05-04T14:00:00Z", "team_h_score": 0, "team_a_score": 0, "round": 36, "minutes": 90, "goals_scored": 0, "assists": 0, "clean_sheets": 1, "goals_conceded": 0, "own_goals": 0, "penalties_saved": 0, "penalties_missed": 0, "yellow_cards": 0, "red_cards": 0, "saves": 3, "bonus": 3, "bps": 31, "influence": "30.6", "creativity": "0.0", "threat": "0.0", "ict_index": "3.1", "starts": 1, "expected_goals": "0.00", "expected_assists": "0.00", "expected_goal_involvements": "0.00", "expected_goals_conceded": "1.19", "value": 47, "transfers_balance": 1499, "selected": 516515, "transfers_in": 17181, "transfers_out": 15682}, {"element": 101, "fixture": 362, "opponent_team": 3, "total_points": 3, "was_home": false, "kickoff_time": "2024-05-11T14:00:00Z", "team_h_score": 1, "team_a_score": 2, "round": 37, "minutes": 90, "goals_scored": 0, "assists": 0, "clean_sheets": 0, "goals_conceded": 1, "own_goals": 0, "penalties_saved": 0, "penalties_missed": 0, "yellow_cards": 0, "red_cards": 0, "saves": 3, "bonus": 0, "bps": 16, "influence": "23.2", "creativity": "10.0", "threat": "0.0", "ict_index": "3.3", "starts": 1, "expected_goals": "0.00", "expected_assists": "0.00", "expected_goal_involvements": "0.00", "expected_goals_conceded": "0.69", "value": 47, "transfers_balance": -15355, "selected": 494875, "transfers_in": 14144, "transfers_out": 29499}, {"element": 101, "fixture": 372, "opponent_team": 15, "total_points": 1, "was_home": true, "kickoff_time": "2024-05-19T15:00:00Z", "team_h_score": 2, "team_a_score": 4, "round": 38, "minutes": 90, "goals_scored": 0, "assists": 0, "clean_sheets": 0, "goals_conceded": 4, "own_goals": 0, "penalties_saved": 0, "penalties_missed": 0, "yellow_cards": 0, "red_cards": 0, "saves": 3, "bonus": 0, "bps": 16, "influence": "21.2", "creativity": "0.0", "threat": "0.0", "ict_index": "2.1", "starts": 1, "expected_goals": "0.00", "expected_assists": "0.00", "expected_goal_involvements": "0.00", "expected_goals_conceded": "3.41", "value": 47, "transfers_balance": -11933, "selected": 487675, "transfers_in": 10956, "transfers_out": 22889}], "history_past": [{"season_name": "2023/24", "element_code": 118342, "start_cost": 45, "end_cost": 47, "total_points": 119, "minutes": 3285, "goals_scored": 0, "assists": 1, "clean_sheets": 7, "goals_conceded": 63, "own_goals": 0, "penalties_saved": 0, "penalties_missed": 0, "yellow_cards": 3, "red_cards": 0, "saves": 115, "bonus": 12, "bps": 685, "influence": "921.2", "creativity": "40.3", "threat": "0.0", "ict_index": "96.2", "starts": 37, "expected_goals": "0.00", "expected_assists": "0.14", "expected_goal_involvements": "0.14", "expected_goals_conceded": "54.01"}]}