{"fixtures": [], "history": [{"element": 222, "fixture": 7, "opponent_team": 17, "total_points": 0, "was_home": false, "kickoff_time": "2023-08-12T14:00:00Z", "team_h_score": 0, "team_a_score": 1, "round": 1, "minutes": 0, "goals_scored": 0, "assists": 0, "clean_sheets": 0, "goals_conceded": 0, "own_goals": 0, "penalties_saved": 0, "penalties_missed": 0, "yellow_cards": 0, "red_cards": 0, "saves": 0, "bonus": 0, "bps": 0, "influence": "0.0", "creativity": "0.0", "threat": "0.0", "ict_index": "0.0", "starts": 0, "expected_goals": "0.00", "expected_assists": "0.00", "expected_goal_involvements": "0.00", "expected_goals_conceded": "0.00", "value": 45, "transfers_balance": 0, "selected": 11232, "transfers_in": 0, "transfers_out": 0}, {"element": 222, "fixture": 12, "opponent_team": 1, "total_points": 0, "was_home": true, "kickoff_time": "2023-08-21T19:00:00Z", "team_h_score": 0, "team_a_score": 1, "round": 2, "minutes": 0, "goals_scored": 0, "assists": 0, "clean_sheets": 0, "goals_conceded": 0, "own_goals": 0, "penalties_saved": 0, "penalties_missed": 0, "yellow_cards": 0, "red_cards": 0, "saves": 0, "bonus": 0, "bps": 0, "influence": "0.0", "creativity": "0.0", "threat": "0.0", "ict_index": "0.0", "starts": 0, "expected_goals": "0.00", "expected_assists": "0.00", "expected_goal_involvements": "0.00", "expected_goals_conceded": "0.00", "value": 45, "transfers_balance": -1434, "selected": 11895, "transfers_in": 388, "transfers_out": 1822}, {"element": 222, "fixture": 23, "opponent_team": 4, "total_points": 0, "was_home": false, "kickoff_time": "2023-08-26T14:00:00Z", "team_h_score": 1, "team_a_score": 1, "round": 3, "minutes": 0, "goals_scored": 0, "assists": 0, "clean_sheets": 0, "goals_conceded": 0, "own_goals": 0, "penalties_saved": 0, "penalties_missed": 0, "yellow_cards": 0, "red_cards": 0, "saves": 0, "bonus": 0, "bps": 0, "influence": "0.0", "creativity": "0.0", "threat": "0.0", "ict_index": "0.0", "starts": 0, "expected_goals": "0.00", "expected_assists": "0.00", "expected_goal_involvements": "0.00", "expected_goals_conceded": "0.00", "value": 45, "transfers_balance": -928, "selected": 11635, "transfers_in": 376, "transfers_out": 1304}, {"element": 222, "fixture": 36, "opponent_team": 20, "total_points": 0, "was_home": true, "kickoff_time": "2023-09-03T13:00:00Z", "team_h_score": 3, "team_a_score": 2, "round": 4, "minutes": 0, "goals_scored": 0, "assists": 0, "clean_sheets": 0, "goals_conceded": 0, "own_goals": 0, "penalties_saved": 0, "penalties_missed": 0, "yellow_cards": 0, "red_cards": 0, "saves": 0, "bonus": 0, "bps": 0, "influence": "0.0", "creativity": "0.0", "threat": "0.0", "ict_index": "0.0", "starts": 0, "expected_goals": "0.00", "expected_assists": "0.00", "expected_goal_involvements": "0.00", "expected_goals_conceded": "0.00", "value": 44, "transfers_balance": -838, "selected": 11161, "transfers_in": 364, "transfers_out": 1202}, {"element": 222, "fixture": 41, "opponent_team": 2, "total_points": 0, "was_home": false, "kickoff_time": "2023-09-16T14:00:00Z", "team_h_score": 3, "team_a_score": 1, "round": 5, "minutes": 0, "goals_scored": 0, "assists": 0, "clean_sheets": 0, "goals_conceded": 0, "own_goals": 0, "penalties_saved": 0, "penalties_missed": 0, "yellow_cards": 0, "red_cards": 0, "saves": 0, "bonus": 0, "bps": 0, "influence": "0.0", "creativity": "0.0", "threat": "0.0", "ict_index": "0.0", "starts": 0, "expected_goals": "0.00", "expected_assists": "0.00", "expected_goal_involvements": "0.00", "expected_goals_conceded": "0.00", "value": 44, "transfers_balance": -535, "selected": 10886, "transfers_in": 382, "transfers_out": 917}, {"element": 222, "fixture": 56, "opponent_team": 10, "total_points": 0, "was_home": true, "kickoff_time": "2023-09-23T14:00:00Z", "team_h_score": 0, "team_a_score": 0, "round": 6, "minutes": 0, "goals_scored": 0, "assists": 0, "clean_sheets": 0, "goals_conceded": 0, "own_goals": 0, "penalties_saved": 0, "penalties_missed": 0, "yellow_cards": 0, "red_cards": 0, "saves": 0, "bonus": 0, "bps": 0, "influence": "0.0", "creativity": "0.0", "threat": "0.0", "ict_index": "0.0", "starts": 0, "expected_goals": "0.00", "expected_assists": "0.00", "expected_goal_involvements": "0.00", "expected_goals_conceded": "0.00", "value": 44, "transfers_balance": -373, "selected": 10573, "transfers_in": 202, "transfers_out": 575}, {"element": 222, "fixture": 65, "opponent_team": 14, "total_points": 0, "was_home": false, "kickoff_time": "2023-09-30T14:00:00Z", "team_h_score": 0, "team_a_score": 1, "round": 7, "minutes": 0, "goals_scored": 0, "assists": 0, "clean_sheets": 0, "goals_conceded": 0, "own_goals": 0, "penalties_saved": 0, "penalties_missed": 0, "yellow_cards": 0, "red_cards": 0, "saves": 0, "bonus": 0, "bps": 0, "influence": "0.0", "creativity": "0.0", "threat": "0.0", "ict_index": "0.0", "starts": 0, "expected_goals": "0.00", "expected_assists": "0.00", "expected_goal_involvements": "0.00", "expected_goals_conceded": "0.00", "value": 44, "transfers_balance": -389, "selected": 10257, "transfers_in": 276, "transfers_out": 665}, {"element": 222, "fixture": 74, "opponent_team": 16, "total_points": 6, "was_home": true, "kickoff_time": "2023-10-07T16:30:00Z", "team_h_score": 0, "team_a_score": 0, "round": 8, "minutes": 90, "goals_scored": 0, "assists": 0, "clean_sheets": 1, "goals_conceded": 0, "own_goals": 0, "penalties_saved": 0, "penalties_missed": 0, "yellow_cards": 0, "red_cards": 0, "saves": 0, "bonus": 0, "bps": 24, "influence": "5.4", "creativity": "3.3", "threat": "6.0", "ict_index": "1.5", "starts": 1, "expected_goals": "0.03", "expected_assists": "0.01", "expected_goal_involvements": "0.04", "expected_goals_conceded": "1.18", "value": 44, "transfers_balance": -173, "selected": 10193, "transfers_in": 347, "transfers_out": 520}, {"element": 222, "fixture": 87, "opponent_team": 15, "total_points": 0, "was_home": false, "kickoff_time": "2023-10-21T14:00:00Z", "team_h_score": 4, "team_a_score": 0, "round": 9, "minutes": 0, "goals_scored": 0, "assists": 0, "clean_sheets": 0, "goals_conceded": 0, "own_goals": 0, "penalties_saved": 0, "penalties_missed": 0, "yellow_cards": 0, "red_cards": 0, "saves": 0, "bonus": 0, "bps": 0, "influence": "0.0", "creativity": "0.0", "threat": "0.0", "ict_index": "0.0", "starts": 0, "expected_goals": "0.00", "expected_assists": "0.00", "expected_goal_involvements": "0.00", "expected_goals_conceded": "0.00", "value": 44, "transfers_balance": 707, "selected": 11100, "transfers_in": 1148, "transfers_out": 441}, {"element": 222, "fixture": 96, "opponent_team": 18, "total_points": 1, "was_home": true, "kickoff_time": "2023-10-27T19:00:00Z", "team_h_score": 1, "team_a_score": 2, "round": 10, "minutes": 20, "goals_scored": 0, "assists": 0, "clean_sheets": 0, "goals_conceded": 0, "own_goals": 0, "penalties_saved": 0, "penalties_missed": 0, "yellow_cards": 0, "red_cards": 0, "saves": 0, "bonus": 0, "bps": 3, "influence": "2.6", "creativity": "0.3", "threat": "0.0", "ict_index": "0.3", "starts": 0, "expected_goals": "0.00", "expected_assists": "0.00", "expected_goal_involvements": "0.00", "expected_goals_conceded": "0.25", "value": 44, "transfers_balance": 99, "selected": 11241, "transfers_in": 650, "transfers_out": 551}, {"element": 222, "fixture": 102, "opponent_team": 6, "total_points": 1, "was_home": false, "kickoff_time": "2023-11-04T15:00:00Z", "team_h_score": 0, "team_a_score": 2, "round": 11, "minutes": 20, "goals_scored": 0, "assists": 0, "clean_sheets": 0, "goals_conceded": 0, "own_goals": 0, "penalties_saved": 0, "penalties_missed": 0, "yellow_cards": 0, "red_cards": 0, "saves": 0, "bonus": 0, "bps": 3, "influence": "2.4", "creativity": "0.0", "threat": "0.0", "ict_index": "0.2", "starts": 0, "expected_goals": "0.00", "expected_assists": "0.00", "expected_goal_involvements": "0.00", "expected_goals_conceded": "0.52", "value": 44, "transfers_balance": 392, "selected": 11732, "transfers_in": 860, "transfers_out": 468}, {"element": 222, "fixture": 116, "opponent_team": 9, "total_points": 0, "was_home": true, "kickoff_time": "2023-11-11T15:00:00Z", "team_h_score": 2, "team_a_score": 3, "round": 12, "minutes": 0, "goals_scored": 0, "assists": 0, "clean_sheets": 0, "goals_conceded": 0, "own_goals": 0, "penalties_saved": 0, "penalties_missed": 0, "yellow_cards": 0, "red_cards": 0, "saves": 0, "bonus": 0, "bps": 0, "influence": "0.0", "creativity": "0.0", "threat": "0.0", "ict_index": "0.0", "starts": 0, "expected_goals": "0.00", "expected_assists": "0.00", "expected_goal_involvements": "0.00", "expected_goals_conceded": "0.00", "value": 44, "transfers_balance": -124, "selected": 11609, "transfers_in": 328, "transfers_out": 452}, {"element": 222, "fixture": 125, "opponent_team": 12, "total_points": 0, "was_home": false, "kickoff_time": "2023-11-25T15:00:00Z", "team_h_score": 2, "team_a_score": 1, "round": 13, "minutes": 0, "goals_scored": 0, "assists": 0, "clean_sheets": 0, "goals_conceded": 0, "own_goals": 0, "penalties_saved": 0, "penalties_missed": 0, "yellow_cards": 0, "red_cards": 0, "saves": 0, "bonus": 0, "bps": 0, "influence": "0.0", "creativity": "0.0", "threat": "0.0", "ict_index": "0.0", "starts": 0, "expected_goals": "0.00", "expected_assists": "0.00", "expected_goal_involvements": "0.00", "expected_goals_conceded": "0.00", "value": 44, "transfers_balance": -154, "selected": 11532, "transfers_in": 320, "transfers_out": 474}, {"element": 222, "fixture": 140, "opponent_team": 19, "total_points": 0, "was_home": false, "kickoff_time": "2023-12-03T14:00:00Z", "team_h_score": 1, "team_a_score": 1, "round": 14, "minutes": 0, "goals_scored": 0, "assists": 0, "clean_sheets": 0, "goals_conceded": 0, "own_goals": 0, "penalties_saved": 0, "penalties_missed": 0, "yellow_cards": 0, "red_cards": 0, "saves": 0, "bonus": 0, "bps": 0, "influence": "0.0", "creativity": "0.0", "threat": "0.0", "ict_index": "0.0", "starts": 0, "expected_goals": "0.00", "expected_assists": "0.00", "expected_goal_involvements": "0.00", "expected_goals_conceded": "0.00", "value": 44, "transfers_balance": -254, "selected": 11306, "transfers_in": 128, "transfers_out": 382}, {"element": 222, "fixture": 143, "opponent_team": 3, "total_points": 2, "was_home": true, "kickoff_time": "2023-12-06T19:30:00Z", "team_h_score": 0, "team_a_score": 2, "round": 15, "minutes": 61, "goals_scored": 0, "assists": 0, "clean_sheets": 0, "goals_conceded": 1, "own_goals": 0, "penalties_saved": 0, "penalties_missed": 0, "yellow_cards": 0, "red_cards": 0, "saves": 0, "bonus": 0, "bps": 14, "influence": "12.4", "creativity": "3.3", "threat": "4.0", "ict_index": "2.0", "starts": 0, "expected_goals": "0.00", "expected_assists": "0.01", "expected_goal_involvements": "0.01", "expected_goals_conceded": "0.82", "value": 44, "transfers_balance": -170, "selected": 11174, "transfers_in": 108, "transfers_out": 278}, {"element": 222, "fixture": 153, "opponent_team": 11, "total_points": 1, "was_home": true, "kickoff_time": "2023-12-09T12:30:00Z", "team_h_score": 1, "team_a_score": 2, "round": 16, "minutes": 90, "goals_scored": 0, "assists": 0, "clean_sheets": 0, "goals_conceded": 2, "own_goals": 0, "penalties_saved": 0, "penalties_missed": 0, "yellow_cards": 0, "red_cards": 0, "saves": 0, "bonus": 0, "bps": 7, "influence": "4.6", "creativity": "0.9", "threat": "2.0", "ict_index": "0.8", "starts": 1, "expected_goals": "0.00", "expected_assists": "0.01", "expected_goal_involvements": "0.01", "expected_goals_conceded": "1.25", "value": 44, "transfers_balance": -111, "selected": 11101, "transfers_in": 142, "transfers_out": 253}, {"element": 222, "fixture": 167, "opponent_team": 13, "total_points": 1, "was_home": false, "kickoff_time": "2023-12-16T15:00:00Z", "team_h_score": 2, "team_a_score": 2, "round": 17, "minutes": 90, "goals_scored": 0, "assists": 0, "clean_sheets": 0, "goals_conceded": 2, "own_goals": 0, "penalties_saved": 0, "penalties_missed": 0, "yellow_cards": 0, "red_cards": 0, "saves": 0, "bonus": 0, "bps": 8, "influence": "11.2", "creativity": "0.4", "threat": "0.0", "ict_index": "1.2", "starts": 1, "expected_goals": "0.00", "expected_assists": "0.00", "expected_goal_involvements": "0.00", "expected_goals_conceded": "1.61", "value": 44, "transfers_balance": -75, "selected": 11092, "transfers_in": 248, "transfers_out": 323}, {"element": 222, "fixture": 172, "opponent_team": 5, "total_points": 2, "was_home": true, "kickoff_time": "2023-12-21T20:00:00Z", "team_h_score": 1, "team_a_score": 1, "round": 18, "minutes": 90, "goals_scored": 0, "assists": 0, "clean_sheets": 0, "goals_conceded": 1, "own_goals": 0, "penalties_saved": 0, "penalties_missed": 0, "yellow_cards": 0, "red_cards": 0, "saves": 0, "bonus": 0, "bps": 9, "influence": "12.2", "creativity": "2.9", "threat": "0.0", "ict_index": "1.5", "starts": 1, "expected_goals": "0.00", "expected_assists": "0.01", "expected_goal_involvements": "0.01", "expected_goals_conceded": "1.14", "value": 44, "transfers_balance": 134, "selected": 11321, "transfers_in": 395, "transfers_out": 261}, {"element": 222, "fixture": 186, "opponent_team": 7, "total_points": 1, "was_home": false, "kickoff_time": "2023-12-27T19:30:00Z", "team_h_score": 2, "team_a_score": 1, "round": 19, "minutes": 90, "goals_scored": 0, "assists": 0, "clean_sheets": 0, "goals_conceded": 2, "own_goals": 0, "penalties_saved": 0, "penalties_missed": 0, "yellow_cards": 0, "red_cards": 0, "saves": 0, "bonus": 0, "bps": 16, "influence": "18.6", "creativity": "6.3", "threat": "0.0", "ict_index": "2.5", "starts": 1, "expected_goals": "0.00", "expected_assists": "0.03", "expected_goal_involvements": "0.03", "expected_goals_conceded": "2.74", "value": 44, "transfers_balance": -76, "selected": 11303, "transfers_in": 206, "transfers_out": 282}, {"element": 222, "fixture": 192, "opponent_team": 4, "total_points": 2, "was_home": true, "kickoff_time": "2023-12-30T15:00:00Z", "team_h_score": 3, "team_a_score": 1, "round": 20, "minutes": 90, "goals_scored": 0, "assists": 0, "clean_sheets": 0, "goals_conceded": 1, "own_goals": 0, "penalties_saved": 0, "penalties_missed": 0, "yellow_cards": 0, "red_cards": 0, "saves": 0, "bonus": 0, "bps": 16, "influence": "13.4", "creativity": "5.6", "threat": "0.0", "ict_index": "1.9", "starts": 1, "expected_goals": "0.00", "expected_assists": "0.02", "expected_goal_involvements": "0.02", "expected_goals_conceded": "1.40", "value": 44, "transfers_balance": 461, "selected": 11846, "transfers_in": 740, "transfers_out": 279}, {"element": 222, "fixture": 201, "opponent_team": 1, "total_points": 1, "was_home": false, "kickoff_time": "2024-01-20T12:30:00Z", "team_h_score": 5, "team_a_score": 0, "round": 21, "minutes": 75, "goals_scored": 0, "assists": 0, "clean_sheets": 0, "goals_conceded": 3, "own_goals": 0, "penalties_saved": 0, "penalties_missed": 0, "yellow_cards": 0, "red_cards": 0, "saves": 0, "bonus": 0, "bps": 9, "influence": "13.2", "creativity": "10.8", "threat": "1.0", "ict_index": "2.5", "starts": 1, "expected_goals": "0.01", "expected_assists": "0.00", "expected_goal_involvements": "0.01", "expected_goals_conceded": "2.46", "value": 44, "transfers_balance": -466, "selected": 11477, "transfers_in": 443, "transfers_out": 909}, {"element": 222, "fixture": 212, "opponent_team": 17, "total_points": 0, "was_home": true, "kickoff_time": "2024-01-30T20:00:00Z", "team_h_score": 3, "team_a_score": 2, "round": 22, "minutes": 0, "goals_scored": 0, "assists": 0, "clean_sheets": 0, "goals_conceded": 0, "own_goals": 0, "penalties_saved": 0, "penalties_missed": 0, "yellow_cards": 0, "red_cards": 0, "saves": 0, "bonus": 0, "bps": 0, "influence": "0.0", "creativity": "0.0", "threat": "0.0", "ict_index": "0.0", "starts": 0, "expected_goals": "0.00", "expected_assists": "0.00", "expected_goal_involvements": "0.00", "expected_goals_conceded": "0.00", "value": 44, "transfers_balance": 327, "selected": 11913, "transfers_in": 684, "transfers_out": 357}, {"element": 222, "fixture": 224, "opponent_team": 5, "total_points": 0, "was_home": false, "kickoff_time": "2024-02-03T15:00:00Z", "team_h_score": 4, "team_a_score": 1, "round": 23, "minutes": 0, "goals_scored": 0, "assists": 0, "clean_sheets": 0, "goals_conceded": 0, "own_goals": 0, "penalties_saved": 0, "penalties_missed": 0, "yellow_cards": 0, "red_cards": 0, "saves": 0, "bonus": 0, "bps": 0, "influence": "0.0", "creativity": "0.0", "threat": "0.0", "ict_index": "0.0", "starts": 0, "expected_goals": "0.00", "expected_assists": "0.00", "expected_goal_involvements": "0.00", "expected_goals_conceded": "0.00", "value": 44, "transfers_balance": -358, "selected": 11552, "transfers_in": 83, "transfers_out": 441}, {"element": 222, "fixture": 232, "opponent_team": 7, "total_points": 0, "was_home": true, "kickoff_time": "2024-02-12T20:00:00Z", "team_h_score": 1, "team_a_score": 3, "round": 24, "minutes": 0, "goals_scored": 0, "assists": 0, "clean_sheets": 0, "goals_conceded": 0, "own_goals": 0, "penalties_saved": 0, "penalties_missed": 0, "yellow_cards": 0, "red_cards": 0, "saves": 0, "bonus": 0, "bps": 0, "influence": "0.0", "creativity": "0.0", "threat": "0.0", "ict_index": "0.0", "starts": 0, "expected_goals": "0.00", "expected_assists": "0.00", "expected_goal_involvements": "0.00", "expected_goals_conceded": "0.00", "value": 44, "transfers_balance": -239, "selected": 11363, "transfers_in": 157, "transfers_out": 396}, {"element": 222, "fixture": 243, "opponent_team": 9, "total_points": 0, "was_home": false, "kickoff_time": "2024-02-19T20:00:00Z", "team_h_score": 1, "team_a_score": 1, "round": 25, "minutes": 0, "goals_scored": 0, "assists": 0, "clean_sheets": 0, "goals_conceded": 0, "own_goals": 0, "penalties_saved": 0, "penalties_missed": 0, "yellow_cards": 0, "red_cards": 0, "saves": 0, "bonus": 0, "bps": 0, "influence": "0.0", "creativity": "0.0", "threat": "0.0", "ict_index": "0.0", "starts": 0, "expected_goals": "0.00", "expected_assists": "0.00", "expected_goal_involvements": "0.00", "expected_goals_conceded": "0.00", "value": 44, "transfers_balance": -128, "selected": 11269, "transfers_in": 172, "transfers_out": 300}, {"element": 222, "fixture": 256, "opponent_team": 6, "total_points": 0, "was_home": true, "kickoff_time": "2024-02-24T15:00:00Z", "team_h_score": 3, "team_a_score": 0, "round": 26, "minutes": 0, "goals_scored": 0, "assists": 0, "clean_sheets": 0, "goals_conceded": 0, "own_goals": 0, "penalties_saved": 0, "penalties_missed": 0, "yellow_cards": 0, "red_cards": 0, "saves": 0, "bonus": 0, "bps": 0, "influence": "0.0", "creativity": "0.0", "threat": "0.0", "ict_index": "0.0", "starts": 0, "expected_goals": "0.00", "expected_assists": "0.00", "expected_goal_involvements": "0.00", "expected_goals_conceded": "0.00", "value": 44, "transfers_balance": -63, "selected": 11361, "transfers_in": 259, "transfers_out": 322}, {"element": 222, "fixture": 270, "opponent_team": 18, "total_points": 0, "was_home": false, "kickoff_time": "2024-03-02T15:00:00Z", "team_h_score": 3, "team_a_score": 1, "round": 27, "minutes": 0, "goals_scored": 0, "assists": 0, "clean_sheets": 0, "goals_conceded": 0, "own_goals": 0, "penalties_saved": 0, "penalties_missed": 0, "yellow_cards": 0, "red_cards": 0, "saves": 0, "bonus": 0, "bps": 0, "influence": "0.0", "creativity": "0.0", "threat": "0.0", "ict_index": "0.0", "starts": 0, "expected_goals": "0.00", "expected_assists": "0.00", "expected_goal_involvements": "0.00", "expected_goals_conceded": "0.00", "value": 43, "transfers_balance": -153, "selected": 11152, "transfers_in": 101, "transfers_out": 254}, {"element": 222, "fixture": 276, "opponent_team": 12, "total_points": 0, "was_home": true, "kickoff_time": "2024-03-09T15:00:00Z", "team_h_score": 1, "team_a_score": 1, "round": 28, "minutes": 0, "goals_scored": 0, "assists": 0, "clean_sheets": 0, "goals_conceded": 0, "own_goals": 0, "penalties_saved": 0, "penalties_missed": 0, "yellow_cards": 0, "red_cards": 0, "saves": 0, "bonus": 0, "bps": 0, "influence": "0.0", "creativity": "0.0", "threat": "0.0", "ict_index": "0.0", "starts": 0, "expected_goals": "0.00", "expected_assists": "0.00", "expected_goal_involvements": "0.00", "expected_goals_conceded": "0.00", "value": 43, "transfers_balance": -122, "selected": 11077, "transfers_in": 120, "transfers_out": 242}, {"element": 222, "fixture": 298, "opponent_team": 16, "total_points": 1, "was_home": false, "kickoff_time": "2024-03-30T15:00:00Z", "team_h_score": 1, "team_a_score": 1, "round": 30, "minutes": 1, "goals_scored": 0, "assists": 0, "clean_sheets": 0, "goals_conceded": 0, "own_goals": 0, "penalties_saved": 0, "penalties_missed": 0, "yellow_cards": 0, "red_cards": 0, "saves": 0, "bonus": 0, "bps": 3, "influence": "0.0", "creativity": "0.0", "threat": "0.0", "ict_index": "0.0", "starts": 0, "expected_goals": "0.00", "expected_assists": "0.00", "expected_goal_involvements": "0.00", "expected_goals_conceded": "0.00", "value": 43, "transfers_balance": -4, "selected": 11025, "transfers_in": 116, "transfers_out": 120}, {"element": 222, "fixture": 302, "opponent_team": 3, "total_points": 0, "was_home": false, "kickoff_time": "2024-04-02T18:45:00Z", "team_h_score": 1, "team_a_score": 0, "round": 31, "minutes": 0, "goals_scored": 0, "assists": 0, "clean_sheets": 0, "goals_conceded": 0, "own_goals": 0, "penalties_saved": 0, "penalties_missed": 0, "yellow_cards": 0, "red_cards": 0, "saves": 0, "bonus": 0, "bps": 0, "influence": "0.0", "creativity": "0.0", "threat": "0.0", "ict_index": "0.0", "starts": 0, "expected_goals": "0.00", "expected_assists": "0.00", "expected_goal_involvements": "0.00", "expected_goals_conceded": "0.00", "value": 43, "transfers_balance": -9, "selected": 11031, "transfers_in": 87, "transfers_out": 96}, {"element": 222, "fixture": 313, "opponent_team": 13, "total_points": 1, "was_home": true, "kickoff_time": "2024-04-06T11:30:00Z", "team_h_score": 2, "team_a_score": 4, "round": 32, "minutes": 15, "goals_scored": 0, "assists": 0, "clean_sheets": 0, "goals_conceded": 0, "own_goals": 0, "penalties_saved": 0, "penalties_missed": 0, "yellow_cards": 0, "red_cards": 0, "saves": 0, "bonus": 0, "bps": 3, "influence": "5.6", "creativity": "0.0", "threat": "0.0", "ict_index": "0.6", "starts": 0, "expected_goals": "0.00", "expected_assists": "0.00", "expected_goal_involvements": "0.00", "expected_goals_conceded": "0.14", "value": 43, "transfers_balance": -34, "selected": 11000, "transfers_in": 81, "transfers_out": 115}, {"element": 222, "fixture": 326, "opponent_team": 11, "total_points": 6, "was_home": false, "kickoff_time": "2024-04-14T13:00:00Z", "team_h_score": 0, "team_a_score": 1, "round": 33, "minutes": 76, "goals_scored": 0, "assists": 0, "clean_sheets": 1, "goals_conceded": 0, "own_goals": 0, "penalties_saved": 0, "penalties_missed": 0, "yellow_cards": 0, "red_cards": 0, "saves": 0, "bonus": 0, "bps": 20, "influence": "15.8", "creativity": "0.1", "threat": "0.0", "ict_index": "1.6", "starts": 1, "expected_goals": "0.00", "expected_assists": "0.00", "expected_goal_involvements": "0.00", "expected_goals_conceded": "2.31", "value": 43, "transfers_balance": -47, "selected": 10977, "transfers_in": 75, "transfers_out": 122}, {"element": 222, "fixture": 333, "opponent_team": 19, "total_points": 1, "was_home": true, "kickoff_time": "2024-04-21T14:00:00Z", "team_h_score": 5, "team_a_score": 2, "round": 34, "minutes": 90, "goals_scored": 0, "assists": 0, "clean_sheets": 0, "goals_conceded": 2, "own_goals": 0, "penalties_saved": 0, "penalties_missed": 0, "yellow_cards": 0, "red_cards": 0, "saves": 0, "bonus": 0, "bps": 18, "influence": "16.6", "creativity": "1.3", "threat": "0.0", "ict_index": "1.8", "starts": 1, "expected_goals": "0.00", "expected_assists": "0.01", "expected_goal_involvements": "0.01", "expected_goals_conceded": "1.27", "value": 43, "transfers_balance": 3939, "selected": 15313, "transfers_in": 4172, "transfers_out": 233}, {"element": 222, "fixture": 284, "opponent_team": 15, "total_points": 6, "was_home": true, "kickoff_time": "2024-04-24T19:00:00Z", "team_h_score": 2, "team_a_score": 0, "round": 34, "minutes": 90, "goals_scored": 0, "assists": 0, "clean_sheets": 1, "goals_conceded": 0, "own_goals": 0, "penalties_saved": 0, "penalties_missed": 0, "yellow_cards": 0, "red_cards": 0, "saves": 0, "bonus": 0, "bps": 22, "influence": "5.6", "creativity": "11.7", "threat": "0.0", "ict_index": "1.7", "starts": 1, "expected_goals": "0.00", "expected_assists": "0.01", "expected_goal_involvements": "0.01", "expected_goals_conceded": "0.42", "value": 43, "transfers_balance": 3939, "selected": 15313, "transfers_in": 4172, "transfers_out": 233}, {"element": 222, "fixture": 344, "opponent_team": 10, "total_points": 2, "was_home": false, "kickoff_time": "2024-04-27T14:00:00Z", "team_h_score": 1, "team_a_score": 1, "round": 35, "minutes": 90, "goals_scored": 0, "assists": 0, "clean_sheets": 0, "goals_conceded": 1, "own_goals": 0, "penalties_saved": 0, "penalties_missed": 0, "yellow_cards": 0, "red_cards": 0, "saves": 0, "bonus": 0, "bps": 15, "influence": "11.8", "creativity": "2.0", "threat": "1.0", "ict_index": "1.5", "starts": 1, "expected_goals": "0.02", "expected_assists": "0.01", "expected_goal_involvements": "0.03", "expected_goals_conceded": "1.14", "value": 43, "transfers_balance": -89, "selected": 14919, "transfers_in": 564, "transfers_out": 653}, {"element": 222, "fixture": 356, "opponent_team": 14, "total_points": 6, "was_home": true, "kickoff_time": "2024-05-06T19:00:00Z", "team_h_score": 4, "team_a_score": 0, "round": 36, "minutes": 77, "goals_scored": 0, "assists": 0, "clean_sheets": 1, "goals_conceded": 0, "own_goals": 0, "penalties_saved": 0, "penalties_missed": 0, "yellow_cards": 0, "red_cards": 0, "saves": 0, "bonus": 0, "bps": 26, "influence": "11.0", "creativity": "15.8", "threat": "2.0", "ict_index": "2.9", "starts": 1, "expected_goals": "0.00", "expected_assists": "0.08", "expected_goal_involvements": "0.08", "expected_goals_conceded": "0.35", "value": 43, "transfers_balance": -69, "selected": 14879, "transfers_in": 382, "transfers_out": 451}, {"element": 222, "fixture": 370, "opponent_team": 20, "total_points": 5, "was_home": false, "kickoff_time": "2024-05-11T14:00:00Z", "team_h_score": 1, "team_a_score": 3, "round": 37, "minutes": 90, "goals_scored": 0, "assists": 1, "clean_sheets": 0, "goals_conceded": 1, "own_goals": 0, "penalties_saved": 0, "penalties_missed": 0, "yellow_cards": 0, "red_cards": 0, "saves": 0, "bonus": 0, "bps": 17, "influence": "7.6", "creativity": "0.8", "threat": "5.0", "ict_index": "1.3", "starts": 1, "expected_goals": "0.15", "expected_assists": "0.00", "expected_goal_involvements": "0.15", "expected_goals_conceded": "1.57", "value": 43, "transfers_balance": 1036, "selected": 16133, "transfers_in": 1898, "transfers_out": 862}, {"element": 222, "fixture": 376, "opponent_team": 2, "total_points": 6, "was_home": true, "kickoff_time": "2024-05-19T15:00:00Z", "team_h_score": 5, "team_a_score": 0, "round": 38, "minutes": 90, "goals_scored": 0, "assists": 0, "clean_sheets": 1, "goals_conceded": 0, "own_goals": 0, "penalties_saved": 0, "penalties_missed": 0, "yellow_cards": 0, "red_cards": 0, "saves": 0, "bonus": 0, "bps": 26, "influence": "9.6", "creativity": "2.3", "threat": "0.0", "ict_index": "1.2", "starts": 1, "expected_goals": "0.00", "expected_assists": "0.01", "expected_goal_involvements": "0.01", "expected_goals_conceded": "1.08", "value": 43, "transfers_balance": 1445, "selected": 17617, "transfers_in": 1871, "transfers_out": 426}], "history_past": [{"season_name": "2012/13", "element_code": 57328, "start_cost": 40, "end_cost": 41, "total_points": 89, "minutes": 3019, "goals_scored": 1, "assists": 3, "clean_sheets": 6, "goals_conceded": 53, "own_goals": 1, "penalties_saved": 0, "penalties_missed": 0, "yellow_cards": 2, "red_cards": 0, "saves": 0, "bonus": 4, "bps": 0, "influence": "0.0", "creativity": "0.0", "threat": "0.0", "ict_index": "0.0", "starts": 0, "expected_goals": "0.00", "expected_assists": "0.00", "expected_goal_involvements": "0.00", "expected_goals_conceded": "0.00"}, {"season_name": "2013/14", "element_code": 57328, "start_cost": 45, "end_cost": 41, "total_points": 100, "minutes": 1862, "goals_scored": 0, "assists": 5, "clean_sheets": 10, "goals_conceded": 18, "own_goals": 0, "penalties_saved": 0, "penalties_missed": 0, "yellow_cards": 3, "red_cards": 0, "saves": 0, "bonus": 10, "bps": 121, "influence": "0.0", "creativity": "0.0", "threat": "0.0", "ict_index": "0.0", "starts": 0, "expected_goals": "0.00", "expected_assists": "0.00", "expected_goal_involvements": "0.00", "expected_goals_conceded": "0.00"}, {"season_name": "2014/15", "element_code": 57328, "start_cost": 50, "end_cost": 59, "total_points": 142, "minutes": 3146, "goals_scored": 2, "assists": 2, "clean_sheets": 13, "goals_conceded": 32, "own_goals": 0, "penalties_saved": 0, "penalties_missed": 0, "yellow_cards": 4, "red_cards": 0, "saves": 0, "bonus": 15, "bps": 664, "influence": "0.0", "creativity": "0.0", "threat": "0.0", "ict_index": "0.0", "starts": 0, "expected_goals": "0.00", "expected_assists": "0.00", "expected_goal_involvements": "0.00", "expected_goals_conceded": "0.00"}, {"season_name": "2015/16", "element_code": 57328, "start_cost": 55, "end_cost": 52, "total_points": 93, "minutes": 2970, "goals_scored": 1, "assists": 0, "clean_sheets": 10, "goals_conceded": 45, "own_goals": 0, "penalties_saved": 0, "penalties_missed": 0, "yellow_cards": 6, "red_cards": 0, "saves": 0, "bonus": 2, "bps": 567, "influence": "0.0", "creativity": "0.0", "threat": "0.0", "ict_index": "0.0", "starts": 0, "expected_goals": "0.00", "expected_assists": "0.00", "expected_goal_involvements": "0.00", "expected_goals_conceded": "0.00"}, {"season_name": "2016/17", "element_code": 57328, "start_cost": 55, "end_cost": 59, "total_points": 129, "minutes": 3323, "goals_scored": 0, "assists": 2, "clean_sheets": 12, "goals_conceded": 41, "own_goals": 0, "penalties_saved": 0, "penalties_missed": 0, "yellow_cards": 0, "red_cards": 0, "saves": 0, "bonus": 13, "bps": 735, "influence": "512.0", "creativity": "716.5", "threat": "294.0", "ict_index": "152.4", "starts": 0, "expected_goals": "0.00", "expected_assists": "0.00", "expected_goal_involvements": "0.00", "expected_goals_conceded": "0.00"}, {"season_name": "2017/18", "element_code": 57328, "start_cost": 55, "end_cost": 53, "total_points": 7, "minutes": 173, "goals_scored": 0, "assists": 0, "clean_sheets": 1, "goals_conceded": 1, "own_goals": 0, "penalties_saved": 0, "penalties_missed": 0, "yellow_cards": 1, "red_cards": 0, "saves": 0, "bonus": 0, "bps": 25, "influence": "21.8", "creativity": "23.8", "threat": "41.0", "ict_index": "8.7", "starts": 0, "expected_goals": "0.00", "expected_assists": "0.00", "expected_goal_involvements": "0.00", "expected_goals_conceded": "0.00"}, {"season_name": "2018/19", "element_code": 57328, "start_cost": 50, "end_cost": 44, "total_points": 34, "minutes": 1250, "goals_scored": 0, "assists": 1, "clean_sheets": 3, "goals_conceded": 26, "own_goals": 0, "penalties_saved": 0, "penalties_missed": 0, "yellow_cards": 2, "red_cards": 0, "saves": 0, "bonus": 0, "bps": 201, "influence": "199.4", "creativity": "100.2", "threat": "72.0", "ict_index": "36.9", "starts": 0, "expected_goals": "0.00", "expected_assists": "0.00", "expected_goal_involvements": "0.00", "expected_goals_conceded": "0.00"}, {"season_name": "2020/21", "element_code": 57328, "start_cost": 45, "end_cost": 45, "total_points": 28, "minutes": 1145, "goals_scored": 0, "assists": 1, "clean_sheets": 2, "goals_conceded": 22, "own_goals": 0, "penalties_saved": 0, "penalties_missed": 0, "yellow_cards": 2, "red_cards": 0, "saves": 0, "bonus": 0, "bps": 172, "influence": "150.8", "creativity": "84.3", "threat": "34.0", "ict_index": "27.2", "starts": 0, "expected_goals": "0.00", "expected_assists": "0.00", "expected_goal_involvements": "0.00", "expected_goals_conceded": "0.00"}, {"season_name": "2021/22", "element_code": 57328, "start_cost": 45, "end_cost": 43, "total_points": 59, "minutes": 1351, "goals_scored": 0, "assists": 1, "clean_sheets": 6, "goals_conceded": 12, "own_goals": 0, "penalties_saved": 0, "penalties_missed": 0, "yellow_cards": 1, "red_cards": 0, "saves": 0, "bonus": 4, "bps": 264, "influence": "181.0", "creativity": "99.1", "threat": "17.0", "ict_index": "29.9", "starts": 0, "expected_goals": "0.00", "expected_assists": "0.00", "expected_goal_involvements": "0.00", "expected_goals_conceded": "0.00"}, {"season_name": "2022/23", "element_code": 57328, "start_cost": 45, "end_cost": 45, "total_points": 44, "minutes": 1638, "goals_scored": 0, "assists": 0, "clean_sheets": 3, "goals_conceded": 23, "own_goals": 0, "penalties_saved": 0, "penalties_missed": 0, "yellow_cards": 3, "red_cards": 0, "saves": 0, "bonus": 0, "bps": 246, "influence": "203.6", "creativity": "124.9", "threat": "8.0", "ict_index": "33.6", "starts": 19, "expected_goals": "0.00", "expected_assists": "0.60", "expected_goal_involvements": "0.60", "expected_goals_conceded": "26.26"}, {"season_name": "2023/24", "element_code": 57328, "start_cost": 45, "end_cost": 43, "total_points": 52, "minutes": 1335, "goals_scored": 0, "assists": 1, "clean_sheets": 5, "goals_conceded": 16, "own_goals": 0, "penalties_saved": 0, "penalties_missed": 0, "yellow_cards": 0, "red_cards": 0, "saves": 0, "bonus": 0, "bps": 259, "influence": "179.6", "creativity": "67.8", "threat": "21.0", "ict_index": "27.0", "starts": 14, "expected_goals": "0.21", "expected_assists": "0.21", "expected_goal_involvements": "0.42", "expected_goals_conceded": "21.65"}]}