{"fixtures": [], "history": [{"element": 539, "fixture": 3, "opponent_team": 3, "total_points": 1, "was_home": false, "kickoff_time": "2023-08-12T14:00:00Z", "team_h_score": 1, "team_a_score": 1, "round": 1, "minutes": 90, "goals_scored": 0, "assists": 0, "clean_sheets": 0, "goals_conceded": 1, "own_goals": 0, "penalties_saved": 0, "penalties_missed": 0, "yellow_cards": 1, "red_cards": 0, "saves": 0, "bonus": 0, "bps": 11, "influence": "15.2", "creativity": "29.4", "threat": "16.0", "ict_index": "6.1", "starts": 1, "expected_goals": "0.18", "expected_assists": "0.21", "expected_goal_involvements": "0.39", "expected_goals_conceded": "1.37", "value": 60, "transfers_balance": 0, "selected": 122235, "transfers_in": 0, "transfers_out": 0}, {"element": 539, "fixture": 19, "opponent_team": 7, "total_points": 6, "was_home": true, "kickoff_time": "2023-08-20T15:30:00Z", "team_h_score": 3, "team_a_score": 1, "round": 2, "minutes": 90, "goals_scored": 1, "assists": 0, "clean_sheets": 0, "goals_conceded": 1, "own_goals": 0, "penalties_saved": 0, "penalties_missed": 0, "yellow_cards": 1, "red_cards": 0, "saves": 0, "bonus": 0, "bps": 23, "influence": "44.8", "creativity": "23.0", "threat": "25.0", "ict_index": "9.3", "starts": 1, "expected_goals": "0.85", "expected_assists": "0.04", "expected_goal_involvements": "0.89", "expected_goals_conceded": "2.45", "value": 60, "transfers_balance": -13163, "selected": 131138, "transfers_in": 7579, "transfers_out": 20742}, {"element": 539, "fixture": 24, "opponent_team": 5, "total_points": 2, "was_home": false, "kickoff_time": "2023-08-26T16:30:00Z", "team_h_score": 1, "team_a_score": 3, "round": 3, "minutes": 84, "goals_scored": 0, "assists": 0, "clean_sheets": 0, "goals_conceded": 1, "own_goals": 0, "penalties_saved": 0, "penalties_missed": 0, "yellow_cards": 0, "red_cards": 0, "saves": 0, "bonus": 0, "bps": 11, "influence": "15.2", "creativity": "27.7", "threat": "16.0", "ict_index": "5.9", "starts": 1, "expected_goals": "0.38", "expected_assists": "0.35", "expected_goal_involvements": "0.73", "expected_goals_conceded": "1.16", "value": 60, "transfers_balance": 7949, "selected": 153439, "transfers_in": 24238, "transfers_out": 16289}, {"element": 539, "fixture": 38, "opponent_team": 12, "total_points": 6, "was_home": false, "kickoff_time": "2023-09-01T19:00:00Z", "team_h_score": 1, "team_a_score": 2, "round": 4, "minutes": 90, "goals_scored": 0, "assists": 1, "clean_sheets": 1, "goals_conceded": 0, "own_goals": 0, "penalties_saved": 0, "penalties_missed": 0, "yellow_cards": 0, "red_cards": 0, "saves": 0, "bonus": 0, "bps": 23, "influence": "32.6", "creativity": "25.7", "threat": "4.0", "ict_index": "6.2", "starts": 1, "expected_goals": "0.00", "expected_assists": "0.21", "expected_goal_involvements": "0.21", "expected_goals_conceded": "1.28", "value": 60, "transfers_balance": 10201, "selected": 175157, "transfers_in": 27118, "transfers_out": 16917}, {"element": 539, "fixture": 49, "opponent_team": 13, "total_points": 1, "was_home": true, "kickoff_time": "2023-09-16T14:00:00Z", "team_h_score": 1, "team_a_score": 3, "round": 5, "minutes": 90, "goals_scored": 0, "assists": 0, "clean_sheets": 0, "goals_conceded": 3, "own_goals": 0, "penalties_saved": 0, "penalties_missed": 0, "yellow_cards": 1, "red_cards": 0, "saves": 0, "bonus": 0, "bps": 10, "influence": "13.4", "creativity": "4.8", "threat": "0.0", "ict_index": "1.8", "starts": 1, "expected_goals": "0.00", "expected_assists": "0.18", "expected_goal_involvements": "0.18", "expected_goals_conceded": "3.63", "value": 60, "transfers_balance": -5991, "selected": 176543, "transfers_in": 14910, "transfers_out": 20901}, {"element": 539, "fixture": 57, "opponent_team": 11, "total_points": 3, "was_home": false, "kickoff_time": "2023-09-24T13:00:00Z", "team_h_score": 3, "team_a_score": 1, "round": 6, "minutes": 86, "goals_scored": 0, "assists": 0, "clean_sheets": 0, "goals_conceded": 3, "own_goals": 0, "penalties_saved": 0, "penalties_missed": 0, "yellow_cards": 0, "red_cards": 0, "saves": 0, "bonus": 1, "bps": 24, "influence": "16.0", "creativity": "18.4", "threat": "0.0", "ict_index": "3.4", "starts": 1, "expected_goals": "0.00", "expected_assists": "0.17", "expected_goal_involvements": "0.17", "expected_goals_conceded": "2.71", "value": 60, "transfers_balance": -6487, "selected": 172941, "transfers_in": 7787, "transfers_out": 14274}, {"element": 539, "fixture": 69, "opponent_team": 17, "total_points": 3, "was_home": true, "kickoff_time": "2023-09-30T14:00:00Z", "team_h_score": 2, "team_a_score": 0, "round": 7, "minutes": 90, "goals_scored": 0, "assists": 0, "clean_sheets": 1, "goals_conceded": 0, "own_goals": 0, "penalties_saved": 0, "penalties_missed": 0, "yellow_cards": 0, "red_cards": 0, "saves": 0, "bonus": 0, "bps": 6, "influence": "5.0", "creativity": "22.1", "threat": "12.0", "ict_index": "3.9", "starts": 1, "expected_goals": "0.06", "expected_assists": "0.23", "expected_goal_involvements": "0.29", "expected_goals_conceded": "1.03", "value": 60, "transfers_balance": 12214, "selected": 189945, "transfers_in": 24838, "transfers_out": 12624}, {"element": 539, "fixture": 79, "opponent_team": 15, "total_points": 1, "was_home": true, "kickoff_time": "2023-10-08T13:00:00Z", "team_h_score": 2, "team_a_score": 2, "round": 8, "minutes": 90, "goals_scored": 0, "assists": 0, "clean_sheets": 0, "goals_conceded": 2, "own_goals": 0, "penalties_saved": 0, "penalties_missed": 0, "yellow_cards": 1, "red_cards": 0, "saves": 0, "bonus": 0, "bps": 5, "influence": "5.8", "creativity": "15.7", "threat": "2.0", "ict_index": "2.4", "starts": 1, "expected_goals": "0.00", "expected_assists": "0.11", "expected_goal_involvements": "0.11", "expected_goals_conceded": "1.95", "value": 60, "transfers_balance": -3207, "selected": 187450, "transfers_in": 13745, "transfers_out": 16952}, {"element": 539, "fixture": 81, "opponent_team": 2, "total_points": 2, "was_home": false, "kickoff_time": "2023-10-22T15:30:00Z", "team_h_score": 4, "team_a_score": 1, "round": 9, "minutes": 85, "goals_scored": 0, "assists": 0, "clean_sheets": 0, "goals_conceded": 3, "own_goals": 0, "penalties_saved": 0, "penalties_missed": 0, "yellow_cards": 0, "red_cards": 0, "saves": 0, "bonus": 0, "bps": 7, "influence": "5.0", "creativity": "19.8", "threat": "4.0", "ict_index": "2.9", "starts": 1, "expected_goals": "0.43", "expected_assists": "0.03", "expected_goal_involvements": "0.46", "expected_goals_conceded": "1.71", "value": 60, "transfers_balance": -3994, "selected": 185862, "transfers_in": 10435, "transfers_out": 14429}, {"element": 539, "fixture": 99, "opponent_team": 9, "total_points": 1, "was_home": true, "kickoff_time": "2023-10-29T13:00:00Z", "team_h_score": 0, "team_a_score": 1, "round": 10, "minutes": 90, "goals_scored": 0, "assists": 0, "clean_sheets": 0, "goals_conceded": 1, "own_goals": 0, "penalties_saved": 0, "penalties_missed": 0, "yellow_cards": 1, "red_cards": 0, "saves": 0, "bonus": 0, "bps": 5, "influence": "7.8", "creativity": "35.8", "threat": "9.0", "ict_index": "5.3", "starts": 1, "expected_goals": "0.12", "expected_assists": "0.12", "expected_goal_involvements": "0.24", "expected_goals_conceded": "0.82", "value": 60, "transfers_balance": -8549, "selected": 178078, "transfers_in": 6696, "transfers_out": 15245}, {"element": 539, "fixture": 101, "opponent_team": 4, "total_points": 0, "was_home": false, "kickoff_time": "2023-11-04T15:00:00Z", "team_h_score": 3, "team_a_score": 2, "round": 11, "minutes": 0, "goals_scored": 0, "assists": 0, "clean_sheets": 0, "goals_conceded": 0, "own_goals": 0, "penalties_saved": 0, "penalties_missed": 0, "yellow_cards": 0, "red_cards": 0, "saves": 0, "bonus": 0, "bps": 0, "influence": "0.0", "creativity": "0.0", "threat": "0.0", "ict_index": "0.0", "starts": 0, "expected_goals": "0.00", "expected_assists": "0.00", "expected_goal_involvements": "0.00", "expected_goals_conceded": "0.00", "value": 60, "transfers_balance": -30457, "selected": 147715, "transfers_in": 2284, "transfers_out": 32741}, {"element": 539, "fixture": 119, "opponent_team": 16, "total_points": 9, "was_home": true, "kickoff_time": "2023-11-12T14:00:00Z", "team_h_score": 3, "team_a_score": 2, "round": 12, "minutes": 90, "goals_scored": 1, "assists": 0, "clean_sheets": 0, "goals_conceded": 2, "own_goals": 0, "penalties_saved": 0, "penalties_missed": 0, "yellow_cards": 0, "red_cards": 0, "saves": 0, "bonus": 2, "bps": 28, "influence": "49.6", "creativity": "17.5", "threat": "30.0", "ict_index": "9.7", "starts": 1, "expected_goals": "0.42", "expected_assists": "0.06", "expected_goal_involvements": "0.48", "expected_goals_conceded": "1.64", "value": 60, "transfers_balance": 158, "selected": 149666, "transfers_in": 7034, "transfers_out": 6876}, {"element": 539, "fixture": 122, "opponent_team": 6, "total_points": 2, "was_home": false, "kickoff_time": "2023-11-25T15:00:00Z", "team_h_score": 1, "team_a_score": 2, "round": 13, "minutes": 90, "goals_scored": 0, "assists": 0, "clean_sheets": 0, "goals_conceded": 1, "own_goals": 0, "penalties_saved": 0, "penalties_missed": 0, "yellow_cards": 0, "red_cards": 0, "saves": 0, "bonus": 0, "bps": 23, "influence": "19.4", "creativity": "29.9", "threat": "10.0", "ict_index": "5.9", "starts": 1, "expected_goals": "0.06", "expected_assists": "0.33", "expected_goal_involvements": "0.39", "expected_goals_conceded": "1.27", "value": 60, "transfers_balance": 28817, "selected": 183199, "transfers_in": 33332, "transfers_out": 4515}, {"element": 539, "fixture": 140, "opponent_team": 8, "total_points": 2, "was_home": true, "kickoff_time": "2023-12-03T14:00:00Z", "team_h_score": 1, "team_a_score": 1, "round": 14, "minutes": 90, "goals_scored": 0, "assists": 0, "clean_sheets": 0, "goals_conceded": 1, "own_goals": 0, "penalties_saved": 0, "penalties_missed": 0, "yellow_cards": 0, "red_cards": 0, "saves": 0, "bonus": 0, "bps": 8, "influence": "3.6", "creativity": "21.4", "threat": "2.0", "ict_index": "2.7", "starts": 1, "expected_goals": "0.00", "expected_assists": "0.28", "expected_goal_involvements": "0.28", "expected_goals_conceded": "0.88", "value": 60, "transfers_balance": -2525, "selected": 179112, "transfers_in": 8554, "transfers_out": 11079}, {"element": 539, "fixture": 148, "opponent_team": 18, "total_points": 2, "was_home": false, "kickoff_time": "2023-12-07T20:15:00Z", "team_h_score": 1, "team_a_score": 2, "round": 15, "minutes": 90, "goals_scored": 0, "assists": 0, "clean_sheets": 0, "goals_conceded": 1, "own_goals": 0, "penalties_saved": 0, "penalties_missed": 0, "yellow_cards": 0, "red_cards": 0, "saves": 0, "bonus": 0, "bps": 2, "influence": "14.2", "creativity": "12.8", "threat": "23.0", "ict_index": "5.0", "starts": 1, "expected_goals": "0.15", "expected_assists": "0.03", "expected_goal_involvements": "0.18", "expected_goals_conceded": "1.74", "value": 60, "transfers_balance": -7605, "selected": 171817, "transfers_in": 3297, "transfers_out": 10902}, {"element": 539, "fixture": 155, "opponent_team": 10, "total_points": 2, "was_home": false, "kickoff_time": "2023-12-10T14:00:00Z", "team_h_score": 5, "team_a_score": 0, "round": 16, "minutes": 64, "goals_scored": 0, "assists": 0, "clean_sheets": 0, "goals_conceded": 4, "own_goals": 0, "penalties_saved": 0, "penalties_missed": 0, "yellow_cards": 0, "red_cards": 0, "saves": 0, "bonus": 0, "bps": 9, "influence": "4.8", "creativity": "7.3", "threat": "1.0", "ict_index": "1.3", "starts": 1, "expected_goals": "0.03", "expected_assists": "0.05", "expected_goal_involvements": "0.08", "expected_goals_conceded": "1.54", "value": 60, "transfers_balance": -4519, "selected": 167996, "transfers_in": 3673, "transfers_out": 8192}, {"element": 539, "fixture": 170, "opponent_team": 20, "total_points": 14, "was_home": true, "kickoff_time": "2023-12-17T14:00:00Z", "team_h_score": 3, "team_a_score": 0, "round": 17, "minutes": 86, "goals_scored": 0, "assists": 3, "clean_sheets": 1, "goals_conceded": 0, "own_goals": 0, "penalties_saved": 0, "penalties_missed": 0, "yellow_cards": 0, "red_cards": 0, "saves": 0, "bonus": 2, "bps": 48, "influence": "65.6", "creativity": "64.8", "threat": "5.0", "ict_index": "13.5", "starts": 1, "expected_goals": "0.09", "expected_assists": "0.05", "expected_goal_involvements": "0.14", "expected_goals_conceded": "0.64", "value": 60, "transfers_balance": -4405, "selected": 164170, "transfers_in": 3502, "transfers_out": 7907}, {"element": 539, "fixture": 179, "opponent_team": 14, "total_points": 5, "was_home": true, "kickoff_time": "2023-12-23T12:30:00Z", "team_h_score": 2, "team_a_score": 0, "round": 18, "minutes": 90, "goals_scored": 0, "assists": 1, "clean_sheets": 1, "goals_conceded": 0, "own_goals": 0, "penalties_saved": 0, "penalties_missed": 0, "yellow_cards": 1, "red_cards": 0, "saves": 0, "bonus": 0, "bps": 18, "influence": "28.0", "creativity": "43.3", "threat": "10.0", "ict_index": "8.1", "starts": 1, "expected_goals": "0.06", "expected_assists": "0.37", "expected_goal_involvements": "0.43", "expected_goals_conceded": "0.91", "value": 60, "transfers_balance": 17488, "selected": 184508, "transfers_in": 21252, "transfers_out": 3764}, {"element": 539, "fixture": 181, "opponent_team": 1, "total_points": 1, "was_home": false, "kickoff_time": "2023-12-28T20:15:00Z", "team_h_score": 0, "team_a_score": 2, "round": 19, "minutes": 32, "goals_scored": 0, "assists": 0, "clean_sheets": 0, "goals_conceded": 0, "own_goals": 0, "penalties_saved": 0, "penalties_missed": 0, "yellow_cards": 0, "red_cards": 0, "saves": 0, "bonus": 0, "bps": -1, "influence": "1.6", "creativity": "0.3", "threat": "0.0", "ict_index": "0.2", "starts": 1, "expected_goals": "0.00", "expected_assists": "0.00", "expected_goal_involvements": "0.00", "expected_goals_conceded": "0.19", "value": 60, "transfers_balance": 40606, "selected": 226253, "transfers_in": 46367, "transfers_out": 5761}, {"element": 539, "fixture": 199, "opponent_team": 5, "total_points": 0, "was_home": true, "kickoff_time": "2024-01-02T19:30:00Z", "team_h_score": 0, "team_a_score": 0, "round": 20, "minutes": 0, "goals_scored": 0, "assists": 0, "clean_sheets": 0, "goals_conceded": 0, "own_goals": 0, "penalties_saved": 0, "penalties_missed": 0, "yellow_cards": 0, "red_cards": 0, "saves": 0, "bonus": 0, "bps": 0, "influence": "0.0", "creativity": "0.0", "threat": "0.0", "ict_index": "0.0", "starts": 0, "expected_goals": "0.00", "expected_assists": "0.00", "expected_goal_involvements": "0.00", "expected_goals_conceded": "0.00", "value": 60, "transfers_balance": -11289, "selected": 214185, "transfers_in": 20075, "transfers_out": 31364}, {"element": 539, "fixture": 210, "opponent_team": 17, "total_points": 0, "was_home": false, "kickoff_time": "2024-01-21T14:00:00Z", "team_h_score": 2, "team_a_score": 2, "round": 21, "minutes": 0, "goals_scored": 0, "assists": 0, "clean_sheets": 0, "goals_conceded": 0, "own_goals": 0, "penalties_saved": 0, "penalties_missed": 0, "yellow_cards": 0, "red_cards": 0, "saves": 0, "bonus": 0, "bps": 0, "influence": "0.0", "creativity": "0.0", "threat": "0.0", "ict_index": "0.0", "starts": 0, "expected_goals": "0.00", "expected_assists": "0.00", "expected_goal_involvements": "0.00", "expected_goals_conceded": "0.00", "value": 60, "transfers_balance": -35969, "selected": 177644, "transfers_in": 7240, "transfers_out": 43209}, {"element": 539, "fixture": 217, "opponent_team": 3, "total_points": 0, "was_home": true, "kickoff_time": "2024-02-01T19:30:00Z", "team_h_score": 1, "team_a_score": 1, "round": 22, "minutes": 0, "goals_scored": 0, "assists": 0, "clean_sheets": 0, "goals_conceded": 0, "own_goals": 0, "penalties_saved": 0, "penalties_missed": 0, "yellow_cards": 0, "red_cards": 0, "saves": 0, "bonus": 0, "bps": 0, "influence": "0.0", "creativity": "0.0", "threat": "0.0", "ict_index": "0.0", "starts": 0, "expected_goals": "0.00", "expected_assists": "0.00", "expected_goal_involvements": "0.00", "expected_goals_conceded": "0.00", "value": 60, "transfers_balance": -19480, "selected": 160040, "transfers_in": 677, "transfers_out": 20157}, {"element": 539, "fixture": 228, "opponent_team": 14, "total_points": 0, "was_home": false, "kickoff_time": "2024-02-04T14:00:00Z", "team_h_score": 3, "team_a_score": 0, "round": 23, "minutes": 0, "goals_scored": 0, "assists": 0, "clean_sheets": 0, "goals_conceded": 0, "own_goals": 0, "penalties_saved": 0, "penalties_missed": 0, "yellow_cards": 0, "red_cards": 0, "saves": 0, "bonus": 0, "bps": 0, "influence": "0.0", "creativity": "0.0", "threat": "0.0", "ict_index": "0.0", "starts": 0, "expected_goals": "0.00", "expected_assists": "0.00", "expected_goal_involvements": "0.00", "expected_goals_conceded": "0.00", "value": 60, "transfers_balance": -8600, "selected": 151917, "transfers_in": 126, "transfers_out": 8726}, {"element": 539, "fixture": 239, "opponent_team": 1, "total_points": 0, "was_home": true, "kickoff_time": "2024-02-11T14:00:00Z", "team_h_score": 0, "team_a_score": 6, "round": 24, "minutes": 0, "goals_scored": 0, "assists": 0, "clean_sheets": 0, "goals_conceded": 0, "own_goals": 0, "penalties_saved": 0, "penalties_missed": 0, "yellow_cards": 0, "red_cards": 0, "saves": 0, "bonus": 0, "bps": 0, "influence": "0.0", "creativity": "0.0", "threat": "0.0", "ict_index": "0.0", "starts": 0, "expected_goals": "0.00", "expected_assists": "0.00", "expected_goal_involvements": "0.00", "expected_goals_conceded": "0.00", "value": 60, "transfers_balance": -9813, "selected": 142138, "transfers_in": 177, "transfers_out": 9990}, {"element": 539, "fixture": 248, "opponent_team": 16, "total_points": 0, "was_home": false, "kickoff_time": "2024-02-17T15:00:00Z", "team_h_score": 2, "team_a_score": 0, "round": 25, "minutes": 0, "goals_scored": 0, "assists": 0, "clean_sheets": 0, "goals_conceded": 0, "own_goals": 0, "penalties_saved": 0, "penalties_missed": 0, "yellow_cards": 0, "red_cards": 0, "saves": 0, "bonus": 0, "bps": 0, "influence": "0.0", "creativity": "0.0", "threat": "0.0", "ict_index": "0.0", "starts": 0, "expected_goals": "0.00", "expected_assists": "0.00", "expected_goal_involvements": "0.00", "expected_goals_conceded": "0.00", "value": 60, "transfers_balance": -7383, "selected": 134620, "transfers_in": 106, "transfers_out": 7489}, {"element": 539, "fixture": 259, "opponent_team": 4, "total_points": 2, "was_home": true, "kickoff_time": "2024-02-26T20:00:00Z", "team_h_score": 4, "team_a_score": 2, "round": 26, "minutes": 75, "goals_scored": 0, "assists": 0, "clean_sheets": 0, "goals_conceded": 1, "own_goals": 0, "penalties_saved": 0, "penalties_missed": 0, "yellow_cards": 0, "red_cards": 0, "saves": 0, "bonus": 0, "bps": 8, "influence": "10.0", "creativity": "21.6", "threat": "8.0", "ict_index": "4.0", "starts": 1, "expected_goals": "0.12", "expected_assists": "0.20", "expected_goal_involvements": "0.32", "expected_goals_conceded": "0.33", "value": 60, "transfers_balance": -3116, "selected": 131764, "transfers_in": 248, "transfers_out": 3364}, {"element": 539, "fixture": 263, "opponent_team": 9, "total_points": 2, "was_home": false, "kickoff_time": "2024-03-02T15:00:00Z", "team_h_score": 1, "team_a_score": 3, "round": 27, "minutes": 79, "goals_scored": 0, "assists": 0, "clean_sheets": 0, "goals_conceded": 1, "own_goals": 0, "penalties_saved": 0, "penalties_missed": 0, "yellow_cards": 0, "red_cards": 0, "saves": 0, "bonus": 0, "bps": 3, "influence": "5.4", "creativity": "31.3", "threat": "14.0", "ict_index": "5.1", "starts": 1, "expected_goals": "0.22", "expected_assists": "0.52", "expected_goal_involvements": "0.74", "expected_goals_conceded": "2.52", "value": 60, "transfers_balance": 7259, "selected": 139845, "transfers_in": 8806, "transfers_out": 1547}, {"element": 539, "fixture": 279, "opponent_team": 6, "total_points": 6, "was_home": true, "kickoff_time": "2024-03-10T14:00:00Z", "team_h_score": 2, "team_a_score": 2, "round": 28, "minutes": 90, "goals_scored": 1, "assists": 0, "clean_sheets": 0, "goals_conceded": 2, "own_goals": 0, "penalties_saved": 0, "penalties_missed": 0, "yellow_cards": 1, "red_cards": 0, "saves": 0, "bonus": 0, "bps": 23, "influence": "44.4", "creativity": "17.4", "threat": "33.0", "ict_index": "9.5", "starts": 1, "expected_goals": "0.57", "expected_assists": "0.11", "expected_goal_involvements": "0.68", "expected_goals_conceded": "0.65", "value": 60, "transfers_balance": 5611, "selected": 146052, "transfers_in": 8063, "transfers_out": 2452}, {"element": 539, "fixture": 289, "opponent_team": 2, "total_points": 2, "was_home": true, "kickoff_time": "2024-03-17T14:00:00Z", "team_h_score": 1, "team_a_score": 1, "round": 29, "minutes": 83, "goals_scored": 0, "assists": 0, "clean_sheets": 0, "goals_conceded": 1, "own_goals": 0, "penalties_saved": 0, "penalties_missed": 0, "yellow_cards": 0, "red_cards": 0, "saves": 0, "bonus": 0, "bps": 7, "influence": "12.6", "creativity": "33.8", "threat": "21.0", "ict_index": "6.7", "starts": 1, "expected_goals": "0.23", "expected_assists": "0.16", "expected_goal_involvements": "0.39", "expected_goals_conceded": "0.61", "value": 60, "transfers_balance": 28434, "selected": 269987, "transfers_in": 31170, "transfers_out": 2736}, {"element": 539, "fixture": 297, "opponent_team": 15, "total_points": 5, "was_home": false, "kickoff_time": "2024-03-30T12:30:00Z", "team_h_score": 4, "team_a_score": 3, "round": 30, "minutes": 90, "goals_scored": 0, "assists": 1, "clean_sheets": 0, "goals_conceded": 4, "own_goals": 0, "penalties_saved": 0, "penalties_missed": 0, "yellow_cards": 0, "red_cards": 0, "saves": 0, "bonus": 0, "bps": 20, "influence": "26.4", "creativity": "37.8", "threat": "9.0", "ict_index": "7.3", "starts": 1, "expected_goals": "0.11", "expected_assists": "0.27", "expected_goal_involvements": "0.38", "expected_goals_conceded": "4.07", "value": 60, "transfers_balance": -6425, "selected": 168499, "transfers_in": 6168, "transfers_out": 12593}, {"element": 539, "fixture": 306, "opponent_team": 18, "total_points": 2, "was_home": true, "kickoff_time": "2024-04-02T19:15:00Z", "team_h_score": 1, "team_a_score": 1, "round": 31, "minutes": 90, "goals_scored": 0, "assists": 0, "clean_sheets": 0, "goals_conceded": 1, "own_goals": 0, "penalties_saved": 0, "penalties_missed": 0, "yellow_cards": 0, "red_cards": 0, "saves": 0, "bonus": 0, "bps": 5, "influence": "14.2", "creativity": "5.8", "threat": "4.0", "ict_index": "2.4", "starts": 1, "expected_goals": "0.06", "expected_assists": "0.14", "expected_goal_involvements": "0.20", "expected_goals_conceded": "0.96", "value": 60, "transfers_balance": 856, "selected": 169869, "transfers_in": 6344, "transfers_out": 5488}, {"element": 539, "fixture": 320, "opponent_team": 20, "total_points": 8, "was_home": false, "kickoff_time": "2024-04-06T14:00:00Z", "team_h_score": 1, "team_a_score": 2, "round": 32, "minutes": 90, "goals_scored": 1, "assists": 0, "clean_sheets": 0, "goals_conceded": 1, "own_goals": 0, "penalties_saved": 0, "penalties_missed": 0, "yellow_cards": 1, "red_cards": 0, "saves": 0, "bonus": 2, "bps": 25, "influence": "50.0", "creativity": "30.7", "threat": "17.0", "ict_index": "9.8", "starts": 1, "expected_goals": "0.79", "expected_assists": "0.10", "expected_goal_involvements": "0.89", "expected_goals_conceded": "1.50", "value": 60, "transfers_balance": -2380, "selected": 167936, "transfers_in": 4251, "transfers_out": 6631}, {"element": 539, "fixture": 330, "opponent_team": 10, "total_points": 1, "was_home": true, "kickoff_time": "2024-04-14T13:00:00Z", "team_h_score": 0, "team_a_score": 2, "round": 33, "minutes": 90, "goals_scored": 0, "assists": 0, "clean_sheets": 0, "goals_conceded": 2, "own_goals": 0, "penalties_saved": 0, "penalties_missed": 0, "yellow_cards": 1, "red_cards": 0, "saves": 0, "bonus": 0, "bps": 10, "influence": "15.2", "creativity": "37.8", "threat": "43.0", "ict_index": "9.6", "starts": 1, "expected_goals": "0.19", "expected_assists": "0.15", "expected_goal_involvements": "0.34", "expected_goals_conceded": "3.29", "value": 60, "transfers_balance": 9239, "selected": 177975, "transfers_in": 12488, "transfers_out": 3249}, {"element": 539, "fixture": 333, "opponent_team": 8, "total_points": 2, "was_home": false, "kickoff_time": "2024-04-21T14:00:00Z", "team_h_score": 5, "team_a_score": 2, "round": 34, "minutes": 90, "goals_scored": 0, "assists": 0, "clean_sheets": 0, "goals_conceded": 5, "own_goals": 0, "penalties_saved": 0, "penalties_missed": 0, "yellow_cards": 0, "red_cards": 0, "saves": 0, "bonus": 0, "bps": 4, "influence": "10.4", "creativity": "16.7", "threat": "0.0", "ict_index": "2.7", "starts": 1, "expected_goals": "0.00", "expected_assists": "0.01", "expected_goal_involvements": "0.01", "expected_goals_conceded": "2.47", "value": 60, "transfers_balance": -7305, "selected": 169994, "transfers_in": 3143, "transfers_out": 10448}, {"element": 539, "fixture": 349, "opponent_team": 11, "total_points": 2, "was_home": true, "kickoff_time": "2024-04-27T11:30:00Z", "team_h_score": 2, "team_a_score": 2, "round": 35, "minutes": 90, "goals_scored": 0, "assists": 0, "clean_sheets": 0, "goals_conceded": 2, "own_goals": 0, "penalties_saved": 0, "penalties_missed": 0, "yellow_cards": 0, "red_cards": 0, "saves": 0, "bonus": 0, "bps": 8, "influence": "4.8", "creativity": "2.8", "threat": "8.0", "ict_index": "1.6", "starts": 1, "expected_goals": "0.00", "expected_assists": "0.06", "expected_goal_involvements": "0.06", "expected_goals_conceded": "1.75", "value": 60, "transfers_balance": -6610, "selected": 164621, "transfers_in": 2045, "transfers_out": 8655}, {"element": 539, "fixture": 355, "opponent_team": 7, "total_points": 1, "was_home": false, "kickoff_time": "2024-05-05T13:00:00Z", "team_h_score": 5, "team_a_score": 0, "round": 36, "minutes": 75, "goals_scored": 0, "assists": 0, "clean_sheets": 0, "goals_conceded": 4, "own_goals": 0, "penalties_saved": 0, "penalties_missed": 0, "yellow_cards": 1, "red_cards": 0, "saves": 0, "bonus": 0, "bps": 9, "influence": "8.2", "creativity": "40.5", "threat": "11.0", "ict_index": "6.0", "starts": 1, "expected_goals": "0.06", "expected_assists": "0.14", "expected_goal_involvements": "0.20", "expected_goals_conceded": "3.46", "value": 60, "transfers_balance": -3668, "selected": 161507, "transfers_in": 1204, "transfers_out": 4872}, {"element": 539, "fixture": 369, "opponent_team": 12, "total_points": 2, "was_home": true, "kickoff_time": "2024-05-11T14:00:00Z", "team_h_score": 3, "team_a_score": 1, "round": 37, "minutes": 83, "goals_scored": 0, "assists": 0, "clean_sheets": 0, "goals_conceded": 1, "own_goals": 0, "penalties_saved": 0, "penalties_missed": 0, "yellow_cards": 0, "red_cards": 0, "saves": 0, "bonus": 0, "bps": 11, "influence": "16.2", "creativity": "24.4", "threat": "6.0", "ict_index": "4.7", "starts": 1, "expected_goals": "0.01", "expected_assists": "0.25", "expected_goal_involvements": "0.26", "expected_goals_conceded": "0.42", "value": 60, "transfers_balance": -4256, "selected": 157240, "transfers_in": 1295, "transfers_out": 5551}, {"element": 539, "fixture": 379, "opponent_team": 13, "total_points": 2, "was_home": false, "kickoff_time": "2024-05-19T15:00:00Z", "team_h_score": 3, "team_a_score": 1, "round": 38, "minutes": 85, "goals_scored": 0, "assists": 0, "clean_sheets": 0, "goals_conceded": 3, "own_goals": 0, "penalties_saved": 0, "penalties_missed": 0, "yellow_cards": 0, "red_cards": 0, "saves": 0, "bonus": 0, "bps": 5, "influence": "5.2", "creativity": "2.0", "threat": "0.0", "ict_index": "0.7", "starts": 1, "expected_goals": "0.00", "expected_assists": "0.00", "expected_goal_involvements": "0.00", "expected_goals_conceded": "2.01", "value": 60, "transfers_balance": -2841, "selected": 154854, "transfers_in": 1556, "transfers_out": 4397}], "history_past": [{"season_name": "2022/23", "element_code": 224024, "start_cost": 60, "end_cost": 59, "total_points": 98, "minutes": 2154, "goals_scored": 4, "assists": 5, "clean_sheets": 6, "goals_conceded": 39, "own_goals": 0, "penalties_saved": 0, "penalties_missed": 0, "yellow_cards": 5, "red_cards": 0, "saves": 0, "bonus": 8, "bps": 395, "influence": "504.4", "creativity": "471.9", "threat": "474.0", "ict_index": "145.4", "starts": 27, "expected_goals": "4.39", "expected_assists": "2.62", "expected_goal_involvements": "7.01", "expected_goals_conceded": "33.84"}, {"season_name": "2023/24", "element_code": 224024, "start_cost": 60, "end_cost": 60, "total_points": 100, "minutes": 2627, "goals_scored": 4, "assists": 6, "clean_sheets": 4, "goals_conceded": 52, "own_goals": 0, "penalties_saved": 0, "penalties_missed": 0, "yellow_cards": 10, "red_cards": 0, "saves": 0, "bonus": 7, "bps": 398, "influence": "570.6", "creativity": "722.3", "threat": "343.0", "ict_index": "163.7", "starts": 31, "expected_goals": "5.19", "expected_assists": "4.93", "expected_goal_involvements": "10.12", "expected_goals_conceded": "50.96"}]}